Workbook

Sheet Assumptions
A1: Integrated Vermicompost Unit (proposed new component) - Assumptions (all values in ETB unless stated)
A2: Entirely new planning component: the original document is a poultry pilot work plan and contains no vermicompost data. Every input below is a new assumption at October 2026 prices unless a source is cited. Blue = input; black = formula.
A3: Active scenario (1 = Base, 2 = Downside, 3 = Upside) | C3: 1 | D3: =CHOOSE($C$3,"Base","Downside","Upside") -> Base
A4: How to use: change the yellow scenario cell (C3) or any blue input; every statement recalculates. Replace VERIFY values with local quotations.
A5: Assumption | B5: Unit | C5: Base | D5: Downside | E5: Upside | F5: Active | G5: Status / source / note
A6: 1. Timing (model month 1 = 'Sep.' month of the original poultry schedule; year not stated in source)
A7: Phase 1 construction complete | B7: month | C7: 4 | D7: 5 | E7: 4 | F7: =CHOOSE($C$3,C7,D7,E7) -> 4 | G7: NEW ASSUMPTION (not in original proposal). Aligned with poultry house construction.
A8: Earthworms stocked / operations start | B8: month | C8: 5 | D8: 6 | E8: 5 | F8: =CHOOSE($C$3,C8,D8,E8) -> 5 | G8: NEW ASSUMPTION (not in original proposal).
A9: Phase 2 expansion goes ahead (1 = yes, 0 = no) | B9: switch | C9: 1 | D9: 0 | E9: 1 | F9: =CHOOSE($C$3,C9,D9,E9) -> 1 | G9: NEW ASSUMPTION (not in original proposal). Decision gate at end of PY1 (see business plan). Downside assumes the gate is not passed.
A10: Phase 2 beds operational | B10: month | C10: 17 | D10: 17 | E10: 15 | F10: =CHOOSE($C$3,C10,D10,E10) -> 17 | G10: NEW ASSUMPTION (not in original proposal). Base: PY2 month 5 (Jan.).
A11: 2. Production system and material flow
A12: Phase 1 vermibeds (1 m x 3 m x 0.5 m, lined ground beds under shade) | B12: beds | C12: 16 | D12: 16 | E12: 16 | F12: =CHOOSE($C$3,C12,D12,E12) -> 16 | G12: NEW ASSUMPTION (not in original proposal).
A13: Phase 2 additional vermibeds | B13: beds | C13: 16 | D13: 16 | E13: 16 | F13: =CHOOSE($C$3,C13,D13,E13) -> 16 | G13: NEW ASSUMPTION (not in original proposal).
A14: Pre-composted feed loaded per bed per cycle (fresh weight) | B14: kg | C14: 750 | D14: 700 | E14: 800 | F14: =CHOOSE($C$3,C14,D14,E14) -> 750 | G14: NEW ASSUMPTION (not in original proposal). ~1.5 m3 working volume x ~0.5 t/m3, fed in layers during the cycle. VERIFY
A15: Cycle length incl. harvest and re-bedding | B15: months | C15: 3 | D15: 4 | E15: 3 | F15: =CHOOSE($C$3,C15,D15,E15) -> 3 | G15: NEW ASSUMPTION (not in original proposal). E. fetida processes pre-composted manure in ~45-90 days at 15-35 C and 60-70% moisture (ISFM+ guidance; ASTU thesis used 45 days).
A16: Ramp-up period after stocking (worm multiplication) | B16: months | C16: 6 | D16: 6 | E16: 6 | F16: =CHOOSE($C$3,C16,D16,E16) -> 6 | G16: NEW ASSUMPTION (not in original proposal).
A17: Bed utilisation during ramp-up | B17: % | C17: 0.5 | D17: 0.4 | E17: 0.5 | F17: =CHOOSE($C$3,C17,D17,E17) -> 0.5 | G17: NEW ASSUMPTION (not in original proposal).
A18: Bed utilisation at steady state (water, downtime, losses) | B18: % | C18: 0.85 | D18: 0.7 | E18: 0.9 | F18: =CHOOSE($C$3,C18,D18,E18) -> 0.85 | G18: NEW ASSUMPTION (not in original proposal).
A19: Mass loss during 2-4 week pre-composting (fresh basis) | B19: % of raw | C19: 0.25 | D19: 0.3 | E19: 0.22 | F19: =CHOOSE($C$3,C19,D19,E19) -> 0.25 | G19: NEW ASSUMPTION (not in original proposal). Pre-composting is required for poultry litter (ammonia/salts kill worms; Oklahoma State thesis; 2025 Belarus study).
A20: Dry matter of bed feed | B20: % | C20: 0.3 | D20: 0.3 | E20: 0.3 | F20: =CHOOSE($C$3,C20,D20,E20) -> 0.3 | G20: NEW ASSUMPTION (not in original proposal). VERIFY
A21: Dry-matter loss during vermicomposting | B21: % of DM | C21: 0.35 | D21: 0.4 | E21: 0.33 | F21: =CHOOSE($C$3,C21,D21,E21) -> 0.35 | G21: NEW ASSUMPTION (not in original proposal). Typical 30-45% organic-matter mineralisation. VERIFY
A22: Moisture of product at sale | B22: % | C22: 0.4 | D22: 0.4 | E22: 0.4 | F22: =CHOOSE($C$3,C22,D22,E22) -> 0.4 | G22: NEW ASSUMPTION (not in original proposal). Declare on label; sell by weight at stated moisture.
A23: Screening oversize / rejects (returned to beds, not sold) | B23: % of harvest | C23: 0.1 | D23: 0.15 | E23: 0.08 | F23: =CHOOSE($C$3,C23,D23,E23) -> 0.1 | G23: NEW ASSUMPTION (not in original proposal).
A24: Material retained as worm bedding / inoculum | B24: % of harvest | C24: 0.1 | D24: 0.1 | E24: 0.1 | F24: =CHOOSE($C$3,C24,D24,E24) -> 0.1 | G24: NEW ASSUMPTION (not in original proposal).
A25: Unscreened vermicompost per kg bed feed (computed) | B25: kg/kg | F25: =$F$20*(1-$F$21)/(1-$F$22) -> 0.325 | G25: Dry-matter balance: feed DM x (1 - DM loss) / (1 - product moisture).
A26: Raw feedstock needed per kg SALEABLE product (computed) | B26: kg/kg | F26: =1/((1-$F$19)*$F$25*(1-$F$23-$F$24)) -> 5.1282051 | G26: Formula.
A27: 3. Feedstock
A28: Poultry litter available from the pullet enterprise | B28: t/yr | C28: 8 | D28: 6 | E28: 8 | F28: =CHOOSE($C$3,C28,D28,E28) -> 8 | G28: NEW ASSUMPTION (not in original proposal). ~2 t per 500-bird batch x 4 batches (droppings + sawdust). Depends on poultry enterprise operating. VERIFY
A29: First month litter is available | B29: month | C29: 7 | D29: 8 | E29: 7 | F29: =CHOOSE($C$3,C29,D29,E29) -> 7 | G29: NEW ASSUMPTION (not in original proposal). After first poultry batch.
A30: Poultry litter cost (internal; handling only) | B30: ETB/kg | C30: 0.1 | D30: 0.2 | E30: 0.1 | F30: =CHOOSE($C$3,C30,D30,E30) -> 0.1 | G30: NEW ASSUMPTION (not in original proposal).
A31: Cattle manure / crop residue / coffee pulp, delivered | B31: ETB/kg | C31: 0.5 | D31: 1 | E31: 0.3 | F31: =CHOOSE($C$3,C31,D31,E31) -> 0.5 | G31: NEW ASSUMPTION (not in original proposal). Often free at source; cost is mainly cart transport. Competes with farmers' own use. VERIFY
A32: 4. Market and prices (PY1 prices; escalated annually)
A33: Accessible annual demand at full market development | B33: t/yr | C33: 22 | D33: 12 | E33: 30 | F33: =CHOOSE($C$3,C33,D33,E33) -> 22 | G33: NEW ASSUMPTION (not in original proposal). Hypothesis built up in plan section C (nurseries, horticulture, smallholder adopters). Must be validated by interviews and pilot sales.
A34: Market development: share of demand reachable in PY1 | B34: % | C34: 0.4 | D34: 0.3 | E34: 0.5 | F34: =CHOOSE($C$3,C34,D34,E34) -> 0.4 | G34: NEW ASSUMPTION (not in original proposal).
A35: Market development: share of demand reachable in PY2 | B35: % | C35: 0.7 | D35: 0.6 | E35: 0.8 | F35: =CHOOSE($C$3,C35,D35,E35) -> 0.7 | G35: NEW ASSUMPTION (not in original proposal).
A36: Blended ex-site price of vermicompost incl. 25 kg bag | B36: ETB/kg | C36: 16 | D36: 12 | E36: 20 | F36: =CHOOSE($C$3,C36,D36,E36) -> 16 | G36: NEW ASSUMPTION (not in original proposal). CGIAR/IWMI (Rift Valley, Oct 2025): ETB 1,000/qt to households; ETB 1,600/qt to collectors. Base blends bulk ~13 and bagged ~19. VERIFY
A37: Surplus earthworms sold (from PY2) | B37: kg/yr | C37: 30 | D37: 10 | E37: 60 | F37: =CHOOSE($C$3,C37,D37,E37) -> 30 | G37: NEW ASSUMPTION (not in original proposal). Thin market, mainly projects/NGOs.
A38: Earthworm price | B38: ETB/kg | C38: 350 | D38: 300 | E38: 400 | F38: =CHOOSE($C$3,C38,D38,E38) -> 350 | G38: NEW ASSUMPTION (not in original proposal). CGIAR/IWMI 2025: ETB 300-500/kg producer; 600-800 collectors' resale.
A39: Share of sales collected in month of sale | B39: % | C39: 0.7 | D39: 0.5 | E39: 0.8 | F39: =CHOOSE($C$3,C39,D39,E39) -> 0.7 | G39: NEW ASSUMPTION (not in original proposal).
A40: Annual price escalation | B40: %/yr | C40: 0.12 | D40: 0.08 | E40: 0.12 | F40: =CHOOSE($C$3,C40,D40,E40) -> 0.12 | G40: NEW ASSUMPTION (not in original proposal). CPI 15.3% (Jul 2026).
A41: Annual cost escalation | B41: %/yr | C41: 0.12 | D41: 0.15 | E41: 0.12 | F41: =CHOOSE($C$3,C41,D41,E41) -> 0.12 | G41: NEW ASSUMPTION (not in original proposal).
A42: Demand seasonality index - Sep | B42: index | C42: 0.6 | D42: 0.6 | E42: 0.6 | F42: =CHOOSE($C$3,C42,D42,E42) -> 0.6 | G42: NEW ASSUMPTION (not in original proposal). Peaks before belg and kiremt planting and nursery potting (Jan.-May). Average = 1.0. VERIFY
A43: Demand seasonality index - Oct | B43: index | C43: 0.6 | D43: 0.6 | E43: 0.6 | F43: =CHOOSE($C$3,C43,D43,E43) -> 0.6
A44: Demand seasonality index - Nov | B44: index | C44: 0.7 | D44: 0.7 | E44: 0.7 | F44: =CHOOSE($C$3,C44,D44,E44) -> 0.7
A45: Demand seasonality index - Dec | B45: index | C45: 0.8 | D45: 0.8 | E45: 0.8 | F45: =CHOOSE($C$3,C45,D45,E45) -> 0.8
A46: Demand seasonality index - Jan | B46: index | C46: 1.2 | D46: 1.2 | E46: 1.2 | F46: =CHOOSE($C$3,C46,D46,E46) -> 1.2
A47: Demand seasonality index - Feb | B47: index | C47: 1.5 | D47: 1.5 | E47: 1.5 | F47: =CHOOSE($C$3,C47,D47,E47) -> 1.5
A48: Demand seasonality index - Mar | B48: index | C48: 1.6 | D48: 1.6 | E48: 1.6 | F48: =CHOOSE($C$3,C48,D48,E48) -> 1.6
A49: Demand seasonality index - Apr | B49: index | C49: 1.4 | D49: 1.4 | E49: 1.4 | F49: =CHOOSE($C$3,C49,D49,E49) -> 1.4
A50: Demand seasonality index - May | B50: index | C50: 1.3 | D50: 1.3 | E50: 1.3 | F50: =CHOOSE($C$3,C50,D50,E50) -> 1.3
A51: Demand seasonality index - Jun | B51: index | C51: 1 | D51: 1 | E51: 1 | F51: =CHOOSE($C$3,C51,D51,E51) -> 1
A52: Demand seasonality index - Jul | B52: index | C52: 0.7 | D52: 0.7 | E52: 0.7 | F52: =CHOOSE($C$3,C52,D52,E52) -> 0.7
A53: Demand seasonality index - Aug | B53: index | C53: 0.6 | D53: 0.6 | E53: 0.6 | F53: =CHOOSE($C$3,C53,D53,E53) -> 0.6
A54: 5. Variable costs
A55: Bag size | B55: kg | C55: 25 | D55: 25 | E55: 25 | F55: =CHOOSE($C$3,C55,D55,E55) -> 25 | G55: NEW ASSUMPTION (not in original proposal).
A56: Woven bag + printed label | B56: ETB/bag | C56: 30 | D56: 35 | E56: 28 | F56: =CHOOSE($C$3,C56,D56,E56) -> 30 | G56: NEW ASSUMPTION (not in original proposal). VERIFY
A57: Casual labour: harvest and screening | B57: ETB/kg harvested | C57: 0.6 | D57: 0.8 | E57: 0.5 | F57: =CHOOSE($C$3,C57,D57,E57) -> 0.6 | G57: NEW ASSUMPTION (not in original proposal). ~ETB 250/day casual rate. VERIFY
A58: Casual labour: feedstock handling and turning | B58: ETB/kg raw | C58: 0.15 | D58: 0.2 | E58: 0.12 | F58: =CHOOSE($C$3,C58,D58,E58) -> 0.15 | G58: NEW ASSUMPTION (not in original proposal).
A59: Delivery cost | B59: ETB/kg sold | C59: 0.8 | D59: 1.2 | E59: 0.7 | F59: =CHOOSE($C$3,C59,D59,E59) -> 0.8 | G59: NEW ASSUMPTION (not in original proposal). VERIFY
A60: 6. Fixed costs (PY1 prices)
A61: Paid member-workers, Phase 1 | B61: FTE | C61: 1 | D61: 1 | E61: 1 | F61: =CHOOSE($C$3,C61,D61,E61) -> 1 | G61: NEW ASSUMPTION (not in original proposal). Supervision shared with poultry duty members (integration benefit).
A62: Additional paid workers, Phase 2 | B62: FTE | C62: 0.5 | D62: 0.5 | E62: 0.5 | F62: =CHOOSE($C$3,C62,D62,E62) -> 0.5 | G62: NEW ASSUMPTION (not in original proposal).
A63: Monthly pay per FTE | B63: ETB/month | C63: 6000 | D63: 6000 | E63: 6000 | F63: =CHOOSE($C$3,C63,D63,E63) -> 6000 | G63: NEW ASSUMPTION (not in original proposal). ~ETB 250/day x 24 days. VERIFY
A64: Imputed unpaid member supervision (memo only) | B64: ETB/month | C64: 3000 | D64: 3000 | E64: 3000 | F64: =CHOOSE($C$3,C64,D64,E64) -> 3000 | G64: NEW ASSUMPTION (not in original proposal).
A65: Water per active bed | B65: ETB/bed/month | C65: 30 | D65: 50 | E65: 25 | F65: =CHOOSE($C$3,C65,D65,E65) -> 30 | G65: NEW ASSUMPTION (not in original proposal). Rain-water harvesting reduces this. VERIFY
A66: Laboratory test per batch sample (twice a year) | B66: ETB/test | C66: 6000 | D66: 8000 | E66: 6000 | F66: =CHOOSE($C$3,C66,D66,E66) -> 6000 | G66: NEW ASSUMPTION (not in original proposal). Nutrients, pH, EC, C:N, maturity, pathogens (E. coli/Salmonella). Lab to be identified. VERIFY
A67: Marketing and demonstrations, PY1 | B67: ETB/yr | C67: 15000 | D67: 15000 | E67: 15000 | F67: =CHOOSE($C$3,C67,D67,E67) -> 15000 | G67: NEW ASSUMPTION (not in original proposal).
A68: Marketing and demonstrations, PY2 onward | B68: ETB/yr | C68: 8000 | D68: 8000 | E68: 8000 | F68: =CHOOSE($C$3,C68,D68,E68) -> 8000 | G68: NEW ASSUMPTION (not in original proposal).
A69: Administration | B69: ETB/month | C69: 500 | D69: 500 | E69: 500 | F69: =CHOOSE($C$3,C69,D69,E69) -> 500 | G69: NEW ASSUMPTION (not in original proposal).
A70: Maintenance | B70: % of cumulative capex/yr | C70: 0.05 | D70: 0.05 | E70: 0.05 | F70: =CHOOSE($C$3,C70,D70,E70) -> 0.05 | G70: NEW ASSUMPTION (not in original proposal).
A71: Registration of activity / licence amendment (one-off) | B71: ETB | C71: 2000 | D71: 2000 | E71: 2000 | F71: =CHOOSE($C$3,C71,D71,E71) -> 2000 | G71: NEW ASSUMPTION (not in original proposal). VERIFY
A72: Annual licence renewal | B72: ETB/yr | C72: 1500 | D72: 1500 | E72: 1500 | F72: =CHOOSE($C$3,C72,D72,E72) -> 1500 | G72: NEW ASSUMPTION (not in original proposal). VERIFY
... A74: Purchase price of starter worms | B74: ETB/kg | C74: 450 | D74: 500 | E74: 400 | F74: =CHOOSE($C$3,C74,D74,E74) -> 450 | G74: NEW ASSUMPTION (not in original proposal). CGIAR/IWMI 2025 range. VERIFY
A75: 7. Investment
A76: Phase 1 structures: shade (~120 m2), 16 lined ground beds, 1 m3 tank + gutters, pre-compost bay (store shared with poultry) | B76: ETB | C76: 110000 | D76: 125000 | E76: 100000 | F76: =CHOOSE($C$3,C76,D76,E76) -> 110000 | G76: NEW ASSUMPTION (not in original proposal). Low-cost design: eucalyptus poles, corrugated iron roof (~70k), plastic-lined ground beds with drainage (~1,500 each), rain-water tank. Obtain 3 quotations. VERIFY
A77: Phase 1 tools: screens, wheelbarrows, forks, scale, thermometer, moisture meter, PPE | B77: ETB | C77: 18000 | D77: 20000 | E77: 18000 | F77: =CHOOSE($C$3,C77,D77,E77) -> 18000 | G77: NEW ASSUMPTION (not in original proposal). VERIFY
A78: Phase 2 structures: shade + 16 beds | B78: ETB | C78: 80000 | D78: 90000 | E78: 75000 | F78: =CHOOSE($C$3,C78,D78,E78) -> 80000 | G78: NEW ASSUMPTION (not in original proposal). VERIFY
A79: Phase 2 tools | B79: ETB | C79: 5000 | D79: 6000 | E79: 5000 | F79: =CHOOSE($C$3,C79,D79,E79) -> 5000 | G79: NEW ASSUMPTION (not in original proposal).
A80: Capital grant for Phase 1 (none confirmed) | B80: ETB | C80: 0 | D80: 0 | E80: 0 | F80: =CHOOSE($C$3,C80,D80,E80) -> 0 | G80: NEW ASSUMPTION (not in original proposal). No partner commitment exists. Set >0 only when confirmed in writing.
A81: Useful life - structures | B81: years | C81: 10 | D81: 10 | E81: 10 | F81: =CHOOSE($C$3,C81,D81,E81) -> 10 | G81: NEW ASSUMPTION (not in original proposal).
A82: Useful life - tools | B82: years | C82: 5 | D82: 5 | E82: 5 | F82: =CHOOSE($C$3,C82,D82,E82) -> 5 | G82: NEW ASSUMPTION (not in original proposal).
A83: 8. Financing, tax and appraisal
A84: Month member equity is paid in | B84: month | C84: 1 | D84: 1 | E84: 1 | F84: =CHOOSE($C$3,C84,D84,E84) -> 1 | G84: NEW ASSUMPTION (not in original proposal).
A85: Minimum cash buffer to maintain | B85: ETB | C85: 5000 | D85: 5000 | E85: 5000 | F85: =CHOOSE($C$3,C85,D85,E85) -> 5000 | G85: Assumption; any shortfall below this is shown as additional funding required.
A86: Member cash equity | B86: ETB | C86: 20000 | D86: 20000 | E86: 20000 | F86: =CHOOSE($C$3,C86,D86,E86) -> 20000 | G86: NEW ASSUMPTION (not in original proposal). VERIFY
A87: Loan disbursement month | B87: month | C87: 3 | D87: 3 | E87: 3 | F87: =CHOOSE($C$3,C87,D87,E87) -> 3 | G87: NEW ASSUMPTION (not in original proposal).
A88: Investment loan | B88: ETB | C88: 120000 | D88: 120000 | E88: 120000 | F88: =CHOOSE($C$3,C88,D88,E88) -> 120000 | G88: NEW ASSUMPTION (not in original proposal). No lender identified.
A89: Interest rate | B89: %/yr | C89: 0.22 | D89: 0.26 | E89: 0.2 | F89: =CHOOSE($C$3,C89,D89,E89) -> 0.22 | G89: NEW ASSUMPTION (not in original proposal). NBE policy rate 16% from 13 Jul 2026. VERIFY
A90: Grace period (interest only) | B90: months | C90: 6 | D90: 6 | E90: 6 | F90: =CHOOSE($C$3,C90,D90,E90) -> 6 | G90: NEW ASSUMPTION (not in original proposal).
A91: Repayment period after grace | B91: months | C91: 36 | D91: 36 | E91: 36 | F91: =CHOOSE($C$3,C91,D91,E91) -> 36 | G91: NEW ASSUMPTION (not in original proposal).
A92: Monthly instalment (computed) | B92: ETB/month | F92: =PMT($F$89/12,$F$91,-$F$88) -> 4582.8544 | G92: Formula.
A93: Business income tax provision | B93: % of PBT | C93: 0.1 | D93: 0.1 | E93: 0.1 | F93: =CHOOSE($C$3,C93,D93,E93) -> 0.1 | G93: PLACEHOLDER - verify (see poultry model note).
A94: Discount rate (nominal) | B94: % | C94: 0.25 | D94: 0.25 | E94: 0.25 | F94: =CHOOSE($C$3,C94,D94,E94) -> 0.25 | G94: As poultry model.
A95: Standard variable cost per kg saleable (for inventory valuation) | B95: ETB/kg | F95: =$F$26*($F$31+$F$58)+$F$57/(1-$F$23-$F$24) -> 4.0833333 | G95: Formula (PY1 prices).

Sheet Monthly
A1: Integrated Vermicompost Unit (proposed new component) - Monthly engine (60 months). Month 1 = first month of the original Sep.-Aug. schedule; year not stated in source.
A3: Model month no. | C3: 1 | D3: 2 | E3: 3 | F3: 4 | G3: 5 | H3: 6 | I3: 7 | J3: 8 | K3: 9 | L3: 10 | M3: 11 | N3: 12 | O3: 13 | P3: 14 | Q3: 15 | R3: 16 | S3: 17 | T3: 18 | U3: 19 | V3: 20 | W3: 21 | X3: 22 | Y3: 23 | Z3: 24 | AA3: 25 | AB3: 26 | AC3: 27 | AD3: 28 | AE3: 29 | AF3: 30 | AG3: 31 | AH3: 32 | AI3: 33 | AJ3: 34 | AK3: 35 | AL3: 36 | AM3: 37 | AN3: 38 | AO3: 39 | AP3: 40 | AQ3: 41 | AR3: 42 | AS3: 43 | AT3: 44 | AU3: 45 | AV3: 46 | AW3: 47 | AX3: 48 | AY3: 49 | AZ3: 50 | BA3: 51 | BB3: 52 | BC3: 53 | BD3: 54 | BE3: 55 | BF3: 56 | BG3: 57 | BH3: 58 | BI3: 59 | BJ3: 60
A4: Project year (PY) | C4: =INT((C3-1)/12)+1 -> 1 | D4: =INT((D3-1)/12)+1 -> 1 | E4: =INT((E3-1)/12)+1 -> 1 | F4: =INT((F3-1)/12)+1 -> 1 | G4: =INT((G3-1)/12)+1 -> 1 | H4: =INT((H3-1)/12)+1 -> 1 | I4: =INT((I3-1)/12)+1 -> 1 | J4: =INT((J3-1)/12)+1 -> 1 | ... BJ4: =INT((BJ3-1)/12)+1 -> 5
A5: Calendar month label (year to be confirmed) | C5: Sep | D5: Oct | E5: Nov | F5: Dec | G5: Jan | H5: Feb | I5: Mar | J5: Apr | K5: May | L5: Jun | M5: Jul | N5: Aug | O5: Sep | P5: Oct | Q5: Nov | R5: Dec | S5: Jan | T5: Feb | U5: Mar | V5: Apr | W5: May | X5: Jun | Y5: Jul | Z5: Aug | AA5: Sep | AB5: Oct | AC5: Nov | AD5: Dec | AE5: Jan | AF5: Feb | AG5: Mar | AH5: Apr | AI5: May | AJ5: Jun | AK5: Jul | AL5: Aug | AM5: Sep | AN5: Oct | AO5: Nov | AP5: Dec | AQ5: Jan | AR5: Feb | AS5: Mar | AT5: Apr | AU5: May | AV5: Jun | AW5: Jul | AX5: Aug | AY5: Sep | AZ5: Oct | BA5: Nov | BB5: Dec | BC5: Jan | BD5: Feb | BE5: Mar | BF5: Apr | BG5: May | BH5: Jun | BI5: Jul | BJ5: Aug
A6: ESCALATION
A7: Price index | C7: =(1+Assumptions!$F$40)^(C$4-1) -> 1 | D7: =(1+Assumptions!$F$40)^(D$4-1) -> 1 | E7: =(1+Assumptions!$F$40)^(E$4-1) -> 1 | F7: =(1+Assumptions!$F$40)^(F$4-1) -> 1 | G7: =(1+Assumptions!$F$40)^(G$4-1) -> 1 | H7: =(1+Assumptions!$F$40)^(H$4-1) -> 1 | I7: =(1+Assumptions!$F$40)^(I$4-1) -> 1 | J7: =(1+Assumptions!$F$40)^(J$4-1) -> 1 | ... BJ7: =(1+Assumptions!$F$40)^(BJ$4-1) -> 1.5735194
A8: Cost index | C8: =(1+Assumptions!$F$41)^(C$4-1) -> 1 | D8: =(1+Assumptions!$F$41)^(D$4-1) -> 1 | E8: =(1+Assumptions!$F$41)^(E$4-1) -> 1 | F8: =(1+Assumptions!$F$41)^(F$4-1) -> 1 | G8: =(1+Assumptions!$F$41)^(G$4-1) -> 1 | H8: =(1+Assumptions!$F$41)^(H$4-1) -> 1 | I8: =(1+Assumptions!$F$41)^(I$4-1) -> 1 | J8: =(1+Assumptions!$F$41)^(J$4-1) -> 1 | ... BJ8: =(1+Assumptions!$F$41)^(BJ$4-1) -> 1.5735194
A9: CAPACITY AND MATERIAL FLOW (kg, fresh weight)
A10: Phase 1 beds in operation | C10: =IF(C$3>=Assumptions!$F$8,Assumptions!$F$12,0) -> 0 | D10: =IF(D$3>=Assumptions!$F$8,Assumptions!$F$12,0) -> 0 | E10: =IF(E$3>=Assumptions!$F$8,Assumptions!$F$12,0) -> 0 | F10: =IF(F$3>=Assumptions!$F$8,Assumptions!$F$12,0) -> 0 | G10: =IF(G$3>=Assumptions!$F$8,Assumptions!$F$12,0) -> 16 | H10: =IF(H$3>=Assumptions!$F$8,Assumptions!$F$12,0) -> 16 | I10: =IF(I$3>=Assumptions!$F$8,Assumptions!$F$12,0) -> 16 | J10: =IF(J$3>=Assumptions!$F$8,Assumptions!$F$12,0) -> 16 | ... BJ10: =IF(BJ$3>=Assumptions!$F$8,Assumptions!$F$12,0) -> 16
A11: Phase 2 beds in operation | C11: =IF(AND(Assumptions!$F$9=1,C$3>=Assumptions!$F$10),Assumptions!$F$13,0) -> 0 | D11: =IF(AND(Assumptions!$F$9=1,D$3>=Assumptions!$F$10),Assumptions!$F$13,0) -> 0 | E11: =IF(AND(Assumptions!$F$9=1,E$3>=Assumptions!$F$10),Assumptions!$F$13,0) -> 0 | F11: =IF(AND(Assumptions!$F$9=1,F$3>=Assumptions!$F$10),Assumptions!$F$13,0) -> 0 | G11: =IF(AND(Assumptions!$F$9=1,G$3>=Assumptions!$F$10),Assumptions!$F$13,0) -> 0 | H11: =IF(AND(Assumptions!$F$9=1,H$3>=Assumptions!$F$10),Assumptions!$F$13,0) -> 0 | I11: =IF(AND(Assumptions!$F$9=1,I$3>=Assumptions!$F$10),Assumptions!$F$13,0) -> 0 | J11: =IF(AND(Assumptions!$F$9=1,J$3>=Assumptions!$F$10),Assumptions!$F$13,0) -> 0 | ... BJ11: =IF(AND(Assumptions!$F$9=1,BJ$3>=Assumptions!$F$10),Assumptions!$F$13,0) -> 16
A12: Phase 1 utilisation | C12: =IF(C$3<Assumptions!$F$8,0,IF(C$3<Assumptions!$F$8+Assumptions!$F$16,Assumptions!$F$17,Assumptions!$F$18)) -> 0 | D12: =IF(D$3<Assumptions!$F$8,0,IF(D$3<Assumptions!$F$8+Assumptions!$F$16,Assumptions!$F$17,Assumptions!$F$18)) -> 0 | E12: =IF(E$3<Assumptions!$F$8,0,IF(E$3<Assumptions!$F$8+Assumptions!$F$16,Assumptions!$F$17,Assumptions!$F$18)) -> 0 | F12: =IF(F$3<Assumptions!$F$8,0,IF(F$3<Assumptions!$F$8+Assumptions!$F$16,Assumptions!$F$17,Assumptions!$F$18)) -> 0 | G12: =IF(G$3<Assumptions!$F$8,0,IF(G$3<Assumptions!$F$8+Assumptions!$F$16,Assumptions!$F$17,Assumptions!$F$18)) -> 0.5 | H12: =IF(H$3<Assumptions!$F$8,0,IF(H$3<Assumptions!$F$8+Assumptions!$F$16,Assumptions!$F$17,Assumptions!$F$18)) -> 0.5 | I12: =IF(I$3<Assumptions!$F$8,0,IF(I$3<Assumptions!$F$8+Assumptions!$F$16,Assumptions!$F$17,Assumptions!$F$18)) -> 0.5 | J12: =IF(J$3<Assumptions!$F$8,0,IF(J$3<Assumptions!$F$8+Assumptions!$F$16,Assumptions!$F$17,Assumptions!$F$18)) -> 0.5 | ... BJ12: =IF(BJ$3<Assumptions!$F$8,0,IF(BJ$3<Assumptions!$F$8+Assumptions!$F$16,Assumptions!$F$17,Assumptions!$F$18)) -> 0.85
A13: Phase 2 utilisation | C13: =IF(C$3<Assumptions!$F$10,0,IF(C$3<Assumptions!$F$10+Assumptions!$F$16,Assumptions!$F$17,Assumptions!$F$18)) -> 0 | D13: =IF(D$3<Assumptions!$F$10,0,IF(D$3<Assumptions!$F$10+Assumptions!$F$16,Assumptions!$F$17,Assumptions!$F$18)) -> 0 | E13: =IF(E$3<Assumptions!$F$10,0,IF(E$3<Assumptions!$F$10+Assumptions!$F$16,Assumptions!$F$17,Assumptions!$F$18)) -> 0 | F13: =IF(F$3<Assumptions!$F$10,0,IF(F$3<Assumptions!$F$10+Assumptions!$F$16,Assumptions!$F$17,Assumptions!$F$18)) -> 0 | G13: =IF(G$3<Assumptions!$F$10,0,IF(G$3<Assumptions!$F$10+Assumptions!$F$16,Assumptions!$F$17,Assumptions!$F$18)) -> 0 | H13: =IF(H$3<Assumptions!$F$10,0,IF(H$3<Assumptions!$F$10+Assumptions!$F$16,Assumptions!$F$17,Assumptions!$F$18)) -> 0 | I13: =IF(I$3<Assumptions!$F$10,0,IF(I$3<Assumptions!$F$10+Assumptions!$F$16,Assumptions!$F$17,Assumptions!$F$18)) -> 0 | J13: =IF(J$3<Assumptions!$F$10,0,IF(J$3<Assumptions!$F$10+Assumptions!$F$16,Assumptions!$F$17,Assumptions!$F$18)) -> 0 | ... BJ13: =IF(BJ$3<Assumptions!$F$10,0,IF(BJ$3<Assumptions!$F$10+Assumptions!$F$16,Assumptions!$F$17,Assumptions!$F$18)) -> 0.85
A14: Pre-composted feed loaded into beds | C14: =(C10*C12+C11*C13)*Assumptions!$F$14/Assumptions!$F$15 -> 0 | D14: =(D10*D12+D11*D13)*Assumptions!$F$14/Assumptions!$F$15 -> 0 | E14: =(E10*E12+E11*E13)*Assumptions!$F$14/Assumptions!$F$15 -> 0 | F14: =(F10*F12+F11*F13)*Assumptions!$F$14/Assumptions!$F$15 -> 0 | G14: =(G10*G12+G11*G13)*Assumptions!$F$14/Assumptions!$F$15 -> 2000 | H14: =(H10*H12+H11*H13)*Assumptions!$F$14/Assumptions!$F$15 -> 2000 | I14: =(I10*I12+I11*I13)*Assumptions!$F$14/Assumptions!$F$15 -> 2000 | J14: =(J10*J12+J11*J13)*Assumptions!$F$14/Assumptions!$F$15 -> 2000 | ... BJ14: =(BJ10*BJ12+BJ11*BJ13)*Assumptions!$F$14/Assumptions!$F$15 -> 6800
A15: Raw feedstock collected | C15: =C14/(1-Assumptions!$F$19) -> 0 | D15: =D14/(1-Assumptions!$F$19) -> 0 | E15: =E14/(1-Assumptions!$F$19) -> 0 | F15: =F14/(1-Assumptions!$F$19) -> 0 | G15: =G14/(1-Assumptions!$F$19) -> 2666.6667 | H15: =H14/(1-Assumptions!$F$19) -> 2666.6667 | I15: =I14/(1-Assumptions!$F$19) -> 2666.6667 | J15: =J14/(1-Assumptions!$F$19) -> 2666.6667 | ... BJ15: =BJ14/(1-Assumptions!$F$19) -> 9066.6667
A16: of which poultry litter | C16: =MIN(C15,IF(C$3>=Assumptions!$F$29,Assumptions!$F$28*1000/12,0)) -> 0 | D16: =MIN(D15,IF(D$3>=Assumptions!$F$29,Assumptions!$F$28*1000/12,0)) -> 0 | E16: =MIN(E15,IF(E$3>=Assumptions!$F$29,Assumptions!$F$28*1000/12,0)) -> 0 | F16: =MIN(F15,IF(F$3>=Assumptions!$F$29,Assumptions!$F$28*1000/12,0)) -> 0 | G16: =MIN(G15,IF(G$3>=Assumptions!$F$29,Assumptions!$F$28*1000/12,0)) -> 0 | H16: =MIN(H15,IF(H$3>=Assumptions!$F$29,Assumptions!$F$28*1000/12,0)) -> 0 | I16: =MIN(I15,IF(I$3>=Assumptions!$F$29,Assumptions!$F$28*1000/12,0)) -> 666.66667 | J16: =MIN(J15,IF(J$3>=Assumptions!$F$29,Assumptions!$F$28*1000/12,0)) -> 666.66667 | ... BJ16: =MIN(BJ15,IF(BJ$3>=Assumptions!$F$29,Assumptions!$F$28*1000/12,0)) -> 666.66667
A17: of which manure / residues / coffee pulp | C17: =C15-C16 -> 0 | D17: =D15-D16 -> 0 | E17: =E15-E16 -> 0 | F17: =F15-F16 -> 0 | G17: =G15-G16 -> 2666.6667 | H17: =H15-H16 -> 2666.6667 | I17: =I15-I16 -> 2000 | J17: =J15-J16 -> 2000 | ... BJ17: =BJ15-BJ16 -> 8400
A18: Unscreened vermicompost harvested (lagged one cycle) | C18: =IF(C$3>Assumptions!$F$15,INDEX($C$14:$BJ$14,1,C$3-Assumptions!$F$15),0)*Assumptions!$F$25 -> 0 | D18: =IF(D$3>Assumptions!$F$15,INDEX($C$14:$BJ$14,1,D$3-Assumptions!$F$15),0)*Assumptions!$F$25 -> 0 | E18: =IF(E$3>Assumptions!$F$15,INDEX($C$14:$BJ$14,1,E$3-Assumptions!$F$15),0)*Assumptions!$F$25 -> 0 | F18: =IF(F$3>Assumptions!$F$15,INDEX($C$14:$BJ$14,1,F$3-Assumptions!$F$15),0)*Assumptions!$F$25 -> 0 | G18: =IF(G$3>Assumptions!$F$15,INDEX($C$14:$BJ$14,1,G$3-Assumptions!$F$15),0)*Assumptions!$F$25 -> 0 | H18: =IF(H$3>Assumptions!$F$15,INDEX($C$14:$BJ$14,1,H$3-Assumptions!$F$15),0)*Assumptions!$F$25 -> 0 | I18: =IF(I$3>Assumptions!$F$15,INDEX($C$14:$BJ$14,1,I$3-Assumptions!$F$15),0)*Assumptions!$F$25 -> 0 | J18: =IF(J$3>Assumptions!$F$15,INDEX($C$14:$BJ$14,1,J$3-Assumptions!$F$15),0)*Assumptions!$F$25 -> 650 | ... BJ18: =IF(BJ$3>Assumptions!$F$15,INDEX($C$14:$BJ$14,1,BJ$3-Assumptions!$F$15),0)*Assumptions!$F$25 -> 2210
A19: Screening rejects returned to beds | C19: =C18*Assumptions!$F$23 -> 0 | D19: =D18*Assumptions!$F$23 -> 0 | E19: =E18*Assumptions!$F$23 -> 0 | F19: =F18*Assumptions!$F$23 -> 0 | G19: =G18*Assumptions!$F$23 -> 0 | H19: =H18*Assumptions!$F$23 -> 0 | I19: =I18*Assumptions!$F$23 -> 0 | J19: =J18*Assumptions!$F$23 -> 65 | ... BJ19: =BJ18*Assumptions!$F$23 -> 221
A20: Retained as bedding / inoculum | C20: =C18*Assumptions!$F$24 -> 0 | D20: =D18*Assumptions!$F$24 -> 0 | E20: =E18*Assumptions!$F$24 -> 0 | F20: =F18*Assumptions!$F$24 -> 0 | G20: =G18*Assumptions!$F$24 -> 0 | H20: =H18*Assumptions!$F$24 -> 0 | I20: =I18*Assumptions!$F$24 -> 0 | J20: =J18*Assumptions!$F$24 -> 65 | ... BJ20: =BJ18*Assumptions!$F$24 -> 221
A21: Saleable vermicompost | C21: =C18-C19-C20 -> 0 | D21: =D18-D19-D20 -> 0 | E21: =E18-E19-E20 -> 0 | F21: =F18-F19-F20 -> 0 | G21: =G18-G19-G20 -> 0 | H21: =H18-H19-H20 -> 0 | I21: =I18-I19-I20 -> 0 | J21: =J18-J19-J20 -> 520 | ... BJ21: =BJ18-BJ19-BJ20 -> 1768
A22: Seasonality index | C22: =CHOOSE(MOD(C$3-1,12)+1,Assumptions!$F$42,Assumptions!$F$43,Assumptions!$F$44,Assumptions!$F$45,Assumptions!$F$46,Assumptions!$F$47,Assumptions!$F$48,Assumptions!$F$49,Assumptions!$F$50,Assumptions!$F$51,Assumptions!$F$52,Assumptions!$F$53) -> 0.6 | D22: =CHOOSE(MOD(D$3-1,12)+1,Assumptions!$F$42,Assumptions!$F$43,Assumptions!$F$44,Assumptions!$F$45,Assumptions!$F$46,Assumptions!$F$47,Assumptions!$F$48,Assumptions!$F$49,Assumptions!$F$50,Assumptions!$F$51,Assumptions!$F$52,Assumptions!$F$53) -> 0.6 | E22: =CHOOSE(MOD(E$3-1,12)+1,Assumptions!$F$42,Assumptions!$F$43,Assumptions!$F$44,Assumptions!$F$45,Assumptions!$F$46,Assumptions!$F$47,Assumptions!$F$48,Assumptions!$F$49,Assumptions!$F$50,Assumptions!$F$51,Assumptions!$F$52,Assumptions!$F$53) -> 0.7 | F22: =CHOOSE(MOD(F$3-1,12)+1,Assumptions!$F$42,Assumptions!$F$43,Assumptions!$F$44,Assumptions!$F$45,Assumptions!$F$46,Assumptions!$F$47,Assumptions!$F$48,Assumptions!$F$49,Assumptions!$F$50,Assumptions!$F$51,Assumptions!$F$52,Assumptions!$F$53) -> 0.8 | G22: =CHOOSE(MOD(G$3-1,12)+1,Assumptions!$F$42,Assumptions!$F$43,Assumptions!$F$44,Assumptions!$F$45,Assumptions!$F$46,Assumptions!$F$47,Assumptions!$F$48,Assumptions!$F$49,Assumptions!$F$50,Assumptions!$F$51,Assumptions!$F$52,Assumptions!$F$53) -> 1.2 | H22: =CHOOSE(MOD(H$3-1,12)+1,Assumptions!$F$42,Assumptions!$F$43,Assumptions!$F$44,Assumptions!$F$45,Assumptions!$F$46,Assumptions!$F$47,Assumptions!$F$48,Assumptions!$F$49,Assumptions!$F$50,Assumptions!$F$51,Assumptions!$F$52,Assumptions!$F$53) -> 1.5 | I22: =CHOOSE(MOD(I$3-1,12)+1,Assumptions!$F$42,Assumptions!$F$43,Assumptions!$F$44,Assumptions!$F$45,Assumptions!$F$46,Assumptions!$F$47,Assumptions!$F$48,Assumptions!$F$49,Assumptions!$F$50,Assumptions!$F$51,Assumptions!$F$52,Assumptions!$F$53) -> 1.6 | J22: =CHOOSE(MOD(J$3-1,12)+1,Assumptions!$F$42,Assumptions!$F$43,Assumptions!$F$44,Assumptions!$F$45,Assumptions!$F$46,Assumptions!$F$47,Assumptions!$F$48,Assumptions!$F$49,Assumptions!$F$50,Assumptions!$F$51,Assumptions!$F$52,Assumptions!$F$53) -> 1.4 | ... BJ22: =CHOOSE(MOD(BJ$3-1,12)+1,Assumptions!$F$42,Assumptions!$F$43,Assumptions!$F$44,Assumptions!$F$45,Assumptions!$F$46,Assumptions!$F$47,Assumptions!$F$48,Assumptions!$F$49,Assumptions!$F$50,Assumptions!$F$51,Assumptions!$F$52,Assumptions!$F$53) -> 0.6
A23: Market development factor | C23: =IF(C$4=1,Assumptions!$F$34,IF(C$4=2,Assumptions!$F$35,1)) -> 0.4 | D23: =IF(D$4=1,Assumptions!$F$34,IF(D$4=2,Assumptions!$F$35,1)) -> 0.4 | E23: =IF(E$4=1,Assumptions!$F$34,IF(E$4=2,Assumptions!$F$35,1)) -> 0.4 | F23: =IF(F$4=1,Assumptions!$F$34,IF(F$4=2,Assumptions!$F$35,1)) -> 0.4 | G23: =IF(G$4=1,Assumptions!$F$34,IF(G$4=2,Assumptions!$F$35,1)) -> 0.4 | H23: =IF(H$4=1,Assumptions!$F$34,IF(H$4=2,Assumptions!$F$35,1)) -> 0.4 | I23: =IF(I$4=1,Assumptions!$F$34,IF(I$4=2,Assumptions!$F$35,1)) -> 0.4 | J23: =IF(J$4=1,Assumptions!$F$34,IF(J$4=2,Assumptions!$F$35,1)) -> 0.4 | ... BJ23: =IF(BJ$4=1,Assumptions!$F$34,IF(BJ$4=2,Assumptions!$F$35,1)) -> 1
A24: Demand reachable this month | C24: =Assumptions!$F$33*1000/12*C22*C23 -> 440 | D24: =Assumptions!$F$33*1000/12*D22*D23 -> 440 | E24: =Assumptions!$F$33*1000/12*E22*E23 -> 513.33333 | F24: =Assumptions!$F$33*1000/12*F22*F23 -> 586.66667 | G24: =Assumptions!$F$33*1000/12*G22*G23 -> 880 | H24: =Assumptions!$F$33*1000/12*H22*H23 -> 1100 | I24: =Assumptions!$F$33*1000/12*I22*I23 -> 1173.3333 | J24: =Assumptions!$F$33*1000/12*J22*J23 -> 1026.6667 | ... BJ24: =Assumptions!$F$33*1000/12*BJ22*BJ23 -> 1100
A25: Vermicompost sold | C25: =MIN(C21,C24) -> 0 | D25: =MIN(C26+D21,D24) -> 0 | E25: =MIN(D26+E21,E24) -> 0 | F25: =MIN(E26+F21,F24) -> 0 | G25: =MIN(F26+G21,G24) -> 0 | H25: =MIN(G26+H21,H24) -> 0 | I25: =MIN(H26+I21,I24) -> 0 | J25: =MIN(I26+J21,J24) -> 520 | K25: =MIN(J26+K21,K24) -> 520 | ... BJ25: =MIN(BI26+BJ21,BJ24) -> 1100
A26: Finished-goods inventory (end of month) | C26: =C21-C25 -> 0 | D26: =C26+D21-D25 -> 0 | E26: =D26+E21-E25 -> 0 | F26: =E26+F21-F25 -> 0 | G26: =F26+G21-G25 -> 0 | H26: =G26+H21-H25 -> 0 | I26: =H26+I21-I25 -> 0 | J26: =I26+J21-J25 -> 0 | K26: =J26+K21-K25 -> 0 | ... BJ26: =BI26+BJ21-BJ25 -> 1152.6667
A27: Earthworms sold (kg) | C27: =IF(C$3>12,Assumptions!$F$37/12,0) -> 0 | D27: =IF(D$3>12,Assumptions!$F$37/12,0) -> 0 | E27: =IF(E$3>12,Assumptions!$F$37/12,0) -> 0 | F27: =IF(F$3>12,Assumptions!$F$37/12,0) -> 0 | G27: =IF(G$3>12,Assumptions!$F$37/12,0) -> 0 | H27: =IF(H$3>12,Assumptions!$F$37/12,0) -> 0 | I27: =IF(I$3>12,Assumptions!$F$37/12,0) -> 0 | J27: =IF(J$3>12,Assumptions!$F$37/12,0) -> 0 | ... BJ27: =IF(BJ$3>12,Assumptions!$F$37/12,0) -> 2.5
A28: REVENUE AND COLLECTIONS
A29: Vermicompost sales | C29: =C25*Assumptions!$F$36*C7 -> 0 | D29: =D25*Assumptions!$F$36*D7 -> 0 | E29: =E25*Assumptions!$F$36*E7 -> 0 | F29: =F25*Assumptions!$F$36*F7 -> 0 | G29: =G25*Assumptions!$F$36*G7 -> 0 | H29: =H25*Assumptions!$F$36*H7 -> 0 | I29: =I25*Assumptions!$F$36*I7 -> 0 | J29: =J25*Assumptions!$F$36*J7 -> 8320 | ... BJ29: =BJ25*Assumptions!$F$36*BJ7 -> 27693.941
A30: Earthworm sales | C30: =C27*Assumptions!$F$38*C7 -> 0 | D30: =D27*Assumptions!$F$38*D7 -> 0 | E30: =E27*Assumptions!$F$38*E7 -> 0 | F30: =F27*Assumptions!$F$38*F7 -> 0 | G30: =G27*Assumptions!$F$38*G7 -> 0 | H30: =H27*Assumptions!$F$38*H7 -> 0 | I30: =I27*Assumptions!$F$38*I7 -> 0 | J30: =J27*Assumptions!$F$38*J7 -> 0 | ... BJ30: =BJ27*Assumptions!$F$38*BJ7 -> 1376.8294
A31: Total sales | C31: =C29+C30 -> 0 | D31: =D29+D30 -> 0 | E31: =E29+E30 -> 0 | F31: =F29+F30 -> 0 | G31: =G29+G30 -> 0 | H31: =H29+H30 -> 0 | I31: =I29+I30 -> 0 | J31: =J29+J30 -> 8320 | ... BJ31: =BJ29+BJ30 -> 29070.77
A32: Cash collected | C32: =C31*Assumptions!$F$39 -> 0 | D32: =D31*Assumptions!$F$39+C31*(1-Assumptions!$F$39) -> 0 | E32: =E31*Assumptions!$F$39+D31*(1-Assumptions!$F$39) -> 0 | F32: =F31*Assumptions!$F$39+E31*(1-Assumptions!$F$39) -> 0 | G32: =G31*Assumptions!$F$39+F31*(1-Assumptions!$F$39) -> 0 | H32: =H31*Assumptions!$F$39+G31*(1-Assumptions!$F$39) -> 0 | I32: =I31*Assumptions!$F$39+H31*(1-Assumptions!$F$39) -> 0 | J32: =J31*Assumptions!$F$39+I31*(1-Assumptions!$F$39) -> 5824 | K32: =K31*Assumptions!$F$39+J31*(1-Assumptions!$F$39) -> 8320 | ... BJ32: =BJ31*Assumptions!$F$39+BI31*(1-Assumptions!$F$39) -> 30455.467
A33: Receivables | C33: =C31-C32 -> 0 | D33: =C33+D31-D32 -> 0 | E33: =D33+E31-E32 -> 0 | F33: =E33+F31-F32 -> 0 | G33: =F33+G31-G32 -> 0 | H33: =G33+H31-H32 -> 0 | I33: =H33+I31-I32 -> 0 | J33: =I33+J31-J32 -> 2496 | K33: =J33+K31-K32 -> 2496 | ... BJ33: =BI33+BJ31-BJ32 -> 8721.2311
A34: VARIABLE COSTS
A35: Poultry litter handling | C35: =C16*Assumptions!$F$30*C8 -> 0 | D35: =D16*Assumptions!$F$30*D8 -> 0 | E35: =E16*Assumptions!$F$30*E8 -> 0 | F35: =F16*Assumptions!$F$30*F8 -> 0 | G35: =G16*Assumptions!$F$30*G8 -> 0 | H35: =H16*Assumptions!$F$30*H8 -> 0 | I35: =I16*Assumptions!$F$30*I8 -> 66.666667 | J35: =J16*Assumptions!$F$30*J8 -> 66.666667 | ... BJ35: =BJ16*Assumptions!$F$30*BJ8 -> 104.90129
A36: Other feedstock delivered | C36: =C17*Assumptions!$F$31*C8 -> 0 | D36: =D17*Assumptions!$F$31*D8 -> 0 | E36: =E17*Assumptions!$F$31*E8 -> 0 | F36: =F17*Assumptions!$F$31*F8 -> 0 | G36: =G17*Assumptions!$F$31*G8 -> 1333.3333 | H36: =H17*Assumptions!$F$31*H8 -> 1333.3333 | I36: =I17*Assumptions!$F$31*I8 -> 1000 | J36: =J17*Assumptions!$F$31*J8 -> 1000 | ... BJ36: =BJ17*Assumptions!$F$31*BJ8 -> 6608.7813
A37: Casual labour - feedstock handling | C37: =C15*Assumptions!$F$58*C8 -> 0 | D37: =D15*Assumptions!$F$58*D8 -> 0 | E37: =E15*Assumptions!$F$58*E8 -> 0 | F37: =F15*Assumptions!$F$58*F8 -> 0 | G37: =G15*Assumptions!$F$58*G8 -> 400 | H37: =H15*Assumptions!$F$58*H8 -> 400 | I37: =I15*Assumptions!$F$58*I8 -> 400 | J37: =J15*Assumptions!$F$58*J8 -> 400 | ... BJ37: =BJ15*Assumptions!$F$58*BJ8 -> 2139.9863
A38: Casual labour - harvest and screening | C38: =C18*Assumptions!$F$57*C8 -> 0 | D38: =D18*Assumptions!$F$57*D8 -> 0 | E38: =E18*Assumptions!$F$57*E8 -> 0 | F38: =F18*Assumptions!$F$57*F8 -> 0 | G38: =G18*Assumptions!$F$57*G8 -> 0 | H38: =H18*Assumptions!$F$57*H8 -> 0 | I38: =I18*Assumptions!$F$57*I8 -> 0 | J38: =J18*Assumptions!$F$57*J8 -> 390 | ... BJ38: =BJ18*Assumptions!$F$57*BJ8 -> 2086.4867
A39: Bags and labels | C39: =C25/Assumptions!$F$55*Assumptions!$F$56*C8 -> 0 | D39: =D25/Assumptions!$F$55*Assumptions!$F$56*D8 -> 0 | E39: =E25/Assumptions!$F$55*Assumptions!$F$56*E8 -> 0 | F39: =F25/Assumptions!$F$55*Assumptions!$F$56*F8 -> 0 | G39: =G25/Assumptions!$F$55*Assumptions!$F$56*G8 -> 0 | H39: =H25/Assumptions!$F$55*Assumptions!$F$56*H8 -> 0 | I39: =I25/Assumptions!$F$55*Assumptions!$F$56*I8 -> 0 | J39: =J25/Assumptions!$F$55*Assumptions!$F$56*J8 -> 624 | ... BJ39: =BJ25/Assumptions!$F$55*Assumptions!$F$56*BJ8 -> 2077.0456
A40: Delivery | C40: =C25*Assumptions!$F$59*C8 -> 0 | D40: =D25*Assumptions!$F$59*D8 -> 0 | E40: =E25*Assumptions!$F$59*E8 -> 0 | F40: =F25*Assumptions!$F$59*F8 -> 0 | G40: =G25*Assumptions!$F$59*G8 -> 0 | H40: =H25*Assumptions!$F$59*H8 -> 0 | I40: =I25*Assumptions!$F$59*I8 -> 0 | J40: =J25*Assumptions!$F$59*J8 -> 416 | ... BJ40: =BJ25*Assumptions!$F$59*BJ8 -> 1384.697
A41: Total variable costs | C41: =C35+C36+C37+C38+C39+C40 -> 0 | D41: =D35+D36+D37+D38+D39+D40 -> 0 | E41: =E35+E36+E37+E38+E39+E40 -> 0 | F41: =F35+F36+F37+F38+F39+F40 -> 0 | G41: =G35+G36+G37+G38+G39+G40 -> 1733.3333 | H41: =H35+H36+H37+H38+H39+H40 -> 1733.3333 | I41: =I35+I36+I37+I38+I39+I40 -> 1466.6667 | J41: =J35+J36+J37+J38+J39+J40 -> 2896.6667 | ... BJ41: =BJ35+BJ36+BJ37+BJ38+BJ39+BJ40 -> 14401.898
A42: In-kind grant inputs (none) | C42: =0 -> 0 | D42: =0 -> 0 | E42: =0 -> 0 | F42: =0 -> 0 | G42: =0 -> 0 | H42: =0 -> 0 | I42: =0 -> 0 | J42: =0 -> 0 | ... BJ42: =0 -> 0
A43: Variable costs paid in cash | C43: =C41-C42 -> 0 | D43: =D41-D42 -> 0 | E43: =E41-E42 -> 0 | F43: =F41-F42 -> 0 | G43: =G41-G42 -> 1733.3333 | H43: =H41-H42 -> 1733.3333 | I43: =I41-I42 -> 1466.6667 | J43: =J41-J42 -> 2896.6667 | ... BJ43: =BJ41-BJ42 -> 14401.898
A44: Inventory value at standard cost | C44: =C26*Assumptions!$F$95*C8 -> 0 | D44: =D26*Assumptions!$F$95*D8 -> 0 | E44: =E26*Assumptions!$F$95*E8 -> 0 | F44: =F26*Assumptions!$F$95*F8 -> 0 | G44: =G26*Assumptions!$F$95*G8 -> 0 | H44: =H26*Assumptions!$F$95*H8 -> 0 | I44: =I26*Assumptions!$F$95*I8 -> 0 | J44: =J26*Assumptions!$F$95*J8 -> 0 | ... BJ44: =BJ26*Assumptions!$F$95*BJ8 -> 7406.1185
A45: Increase in inventory value (reduces cost of sales) | C45: =C44 -> 0 | D45: =D44-C44 -> 0 | E45: =E44-D44 -> 0 | F45: =F44-E44 -> 0 | G45: =G44-F44 -> 0 | H45: =H44-G44 -> 0 | I45: =I44-H44 -> 0 | J45: =J44-I44 -> 0 | K45: =K44-J44 -> 0 | ... BJ45: =BJ44-BI44 -> 4292.0363
A46: FIXED COSTS
A47: Operating flag | C47: =IF(C$3>=Assumptions!$F$8-1,1,0) -> 0 | D47: =IF(D$3>=Assumptions!$F$8-1,1,0) -> 0 | E47: =IF(E$3>=Assumptions!$F$8-1,1,0) -> 0 | F47: =IF(F$3>=Assumptions!$F$8-1,1,0) -> 1 | G47: =IF(G$3>=Assumptions!$F$8-1,1,0) -> 1 | H47: =IF(H$3>=Assumptions!$F$8-1,1,0) -> 1 | I47: =IF(I$3>=Assumptions!$F$8-1,1,0) -> 1 | J47: =IF(J$3>=Assumptions!$F$8-1,1,0) -> 1 | ... BJ47: =IF(BJ$3>=Assumptions!$F$8-1,1,0) -> 1
A48: Paid member-workers | C48: =C47*(Assumptions!$F$61+IF(AND(Assumptions!$F$9=1,C$3>=Assumptions!$F$10),Assumptions!$F$62,0))*Assumptions!$F$63*C8 -> 0 | D48: =D47*(Assumptions!$F$61+IF(AND(Assumptions!$F$9=1,D$3>=Assumptions!$F$10),Assumptions!$F$62,0))*Assumptions!$F$63*D8 -> 0 | E48: =E47*(Assumptions!$F$61+IF(AND(Assumptions!$F$9=1,E$3>=Assumptions!$F$10),Assumptions!$F$62,0))*Assumptions!$F$63*E8 -> 0 | F48: =F47*(Assumptions!$F$61+IF(AND(Assumptions!$F$9=1,F$3>=Assumptions!$F$10),Assumptions!$F$62,0))*Assumptions!$F$63*F8 -> 6000 | G48: =G47*(Assumptions!$F$61+IF(AND(Assumptions!$F$9=1,G$3>=Assumptions!$F$10),Assumptions!$F$62,0))*Assumptions!$F$63*G8 -> 6000 | H48: =H47*(Assumptions!$F$61+IF(AND(Assumptions!$F$9=1,H$3>=Assumptions!$F$10),Assumptions!$F$62,0))*Assumptions!$F$63*H8 -> 6000 | I48: =I47*(Assumptions!$F$61+IF(AND(Assumptions!$F$9=1,I$3>=Assumptions!$F$10),Assumptions!$F$62,0))*Assumptions!$F$63*I8 -> 6000 | J48: =J47*(Assumptions!$F$61+IF(AND(Assumptions!$F$9=1,J$3>=Assumptions!$F$10),Assumptions!$F$62,0))*Assumptions!$F$63*J8 -> 6000 | ... BJ48: =BJ47*(Assumptions!$F$61+IF(AND(Assumptions!$F$9=1,BJ$3>=Assumptions!$F$10),Assumptions!$F$62,0))*Assumptions!$F$63*BJ8 -> 14161.674
A49: Water | C49: =(C10+C11)*Assumptions!$F$65*C8 -> 0 | D49: =(D10+D11)*Assumptions!$F$65*D8 -> 0 | E49: =(E10+E11)*Assumptions!$F$65*E8 -> 0 | F49: =(F10+F11)*Assumptions!$F$65*F8 -> 0 | G49: =(G10+G11)*Assumptions!$F$65*G8 -> 480 | H49: =(H10+H11)*Assumptions!$F$65*H8 -> 480 | I49: =(I10+I11)*Assumptions!$F$65*I8 -> 480 | J49: =(J10+J11)*Assumptions!$F$65*J8 -> 480 | ... BJ49: =(BJ10+BJ11)*Assumptions!$F$65*BJ8 -> 1510.5786
A50: Laboratory testing | C50: =IF(AND(C$3>=Assumptions!$F$8+Assumptions!$F$15,MOD(C$3-Assumptions!$F$8-Assumptions!$F$15,6)=0),Assumptions!$F$66*C8,0) -> 0 | D50: =IF(AND(D$3>=Assumptions!$F$8+Assumptions!$F$15,MOD(D$3-Assumptions!$F$8-Assumptions!$F$15,6)=0),Assumptions!$F$66*D8,0) -> 0 | E50: =IF(AND(E$3>=Assumptions!$F$8+Assumptions!$F$15,MOD(E$3-Assumptions!$F$8-Assumptions!$F$15,6)=0),Assumptions!$F$66*E8,0) -> 0 | F50: =IF(AND(F$3>=Assumptions!$F$8+Assumptions!$F$15,MOD(F$3-Assumptions!$F$8-Assumptions!$F$15,6)=0),Assumptions!$F$66*F8,0) -> 0 | G50: =IF(AND(G$3>=Assumptions!$F$8+Assumptions!$F$15,MOD(G$3-Assumptions!$F$8-Assumptions!$F$15,6)=0),Assumptions!$F$66*G8,0) -> 0 | H50: =IF(AND(H$3>=Assumptions!$F$8+Assumptions!$F$15,MOD(H$3-Assumptions!$F$8-Assumptions!$F$15,6)=0),Assumptions!$F$66*H8,0) -> 0 | I50: =IF(AND(I$3>=Assumptions!$F$8+Assumptions!$F$15,MOD(I$3-Assumptions!$F$8-Assumptions!$F$15,6)=0),Assumptions!$F$66*I8,0) -> 0 | J50: =IF(AND(J$3>=Assumptions!$F$8+Assumptions!$F$15,MOD(J$3-Assumptions!$F$8-Assumptions!$F$15,6)=0),Assumptions!$F$66*J8,0) -> 6000 | ... BJ50: =IF(AND(BJ$3>=Assumptions!$F$8+Assumptions!$F$15,MOD(BJ$3-Assumptions!$F$8-Assumptions!$F$15,6)=0),Assumptions!$F$66*BJ8,0) -> 0
A51: Marketing and demonstrations | C51: =C47*IF(C$4=1,Assumptions!$F$67,Assumptions!$F$68)/12*C8 -> 0 | D51: =D47*IF(D$4=1,Assumptions!$F$67,Assumptions!$F$68)/12*D8 -> 0 | E51: =E47*IF(E$4=1,Assumptions!$F$67,Assumptions!$F$68)/12*E8 -> 0 | F51: =F47*IF(F$4=1,Assumptions!$F$67,Assumptions!$F$68)/12*F8 -> 1250 | G51: =G47*IF(G$4=1,Assumptions!$F$67,Assumptions!$F$68)/12*G8 -> 1250 | H51: =H47*IF(H$4=1,Assumptions!$F$67,Assumptions!$F$68)/12*H8 -> 1250 | I51: =I47*IF(I$4=1,Assumptions!$F$67,Assumptions!$F$68)/12*I8 -> 1250 | J51: =J47*IF(J$4=1,Assumptions!$F$67,Assumptions!$F$68)/12*J8 -> 1250 | ... BJ51: =BJ47*IF(BJ$4=1,Assumptions!$F$67,Assumptions!$F$68)/12*BJ8 -> 1049.0129
A52: Administration | C52: =C47*Assumptions!$F$69*C8 -> 0 | D52: =D47*Assumptions!$F$69*D8 -> 0 | E52: =E47*Assumptions!$F$69*E8 -> 0 | F52: =F47*Assumptions!$F$69*F8 -> 500 | G52: =G47*Assumptions!$F$69*G8 -> 500 | H52: =H47*Assumptions!$F$69*H8 -> 500 | I52: =I47*Assumptions!$F$69*I8 -> 500 | J52: =J47*Assumptions!$F$69*J8 -> 500 | ... BJ52: =BJ47*Assumptions!$F$69*BJ8 -> 786.75968
A53: Maintenance | C53: =0 -> 0 | D53: =C82*Assumptions!$F$70/12*D8 -> 0 | E53: =D82*Assumptions!$F$70/12*E8 -> 0 | F53: =E82*Assumptions!$F$70/12*F8 -> 0 | G53: =F82*Assumptions!$F$70/12*G8 -> 533.33333 | H53: =G82*Assumptions!$F$70/12*H8 -> 533.33333 | I53: =H82*Assumptions!$F$70/12*I8 -> 533.33333 | J53: =I82*Assumptions!$F$70/12*J8 -> 533.33333 | K53: =J82*Assumptions!$F$70/12*K8 -> 533.33333 | ... BJ53: =BI82*Assumptions!$F$70/12*BJ8 -> 1463.373
A54: Registration and licences | C54: =IF(C$3=2,Assumptions!$F$71,0)+IF(AND(C$3>12,MOD(C$3,12)=2),Assumptions!$F$72*C8,0) -> 0 | D54: =IF(D$3=2,Assumptions!$F$71,0)+IF(AND(D$3>12,MOD(D$3,12)=2),Assumptions!$F$72*D8,0) -> 2000 | E54: =IF(E$3=2,Assumptions!$F$71,0)+IF(AND(E$3>12,MOD(E$3,12)=2),Assumptions!$F$72*E8,0) -> 0 | F54: =IF(F$3=2,Assumptions!$F$71,0)+IF(AND(F$3>12,MOD(F$3,12)=2),Assumptions!$F$72*F8,0) -> 0 | G54: =IF(G$3=2,Assumptions!$F$71,0)+IF(AND(G$3>12,MOD(G$3,12)=2),Assumptions!$F$72*G8,0) -> 0 | H54: =IF(H$3=2,Assumptions!$F$71,0)+IF(AND(H$3>12,MOD(H$3,12)=2),Assumptions!$F$72*H8,0) -> 0 | I54: =IF(I$3=2,Assumptions!$F$71,0)+IF(AND(I$3>12,MOD(I$3,12)=2),Assumptions!$F$72*I8,0) -> 0 | J54: =IF(J$3=2,Assumptions!$F$71,0)+IF(AND(J$3>12,MOD(J$3,12)=2),Assumptions!$F$72*J8,0) -> 0 | ... BJ54: =IF(BJ$3=2,Assumptions!$F$71,0)+IF(AND(BJ$3>12,MOD(BJ$3,12)=2),Assumptions!$F$72*BJ8,0) -> 0
A55: Starter earthworms (pre-operating, expensed) | C55: =IF(C$3=Assumptions!$F$8,Assumptions!$F$73*Assumptions!$F$74,0) -> 0 | D55: =IF(D$3=Assumptions!$F$8,Assumptions!$F$73*Assumptions!$F$74,0) -> 0 | E55: =IF(E$3=Assumptions!$F$8,Assumptions!$F$73*Assumptions!$F$74,0) -> 0 | F55: =IF(F$3=Assumptions!$F$8,Assumptions!$F$73*Assumptions!$F$74,0) -> 0 | G55: =IF(G$3=Assumptions!$F$8,Assumptions!$F$73*Assumptions!$F$74,0) -> 10800 | H55: =IF(H$3=Assumptions!$F$8,Assumptions!$F$73*Assumptions!$F$74,0) -> 0 | I55: =IF(I$3=Assumptions!$F$8,Assumptions!$F$73*Assumptions!$F$74,0) -> 0 | J55: =IF(J$3=Assumptions!$F$8,Assumptions!$F$73*Assumptions!$F$74,0) -> 0 | ... BJ55: =IF(BJ$3=Assumptions!$F$8,Assumptions!$F$73*Assumptions!$F$74,0) -> 0
A56: Total fixed costs | C56: =C48+C49+C50+C51+C52+C53+C54+C55 -> 0 | D56: =D48+D49+D50+D51+D52+D53+D54+D55 -> 2000 | E56: =E48+E49+E50+E51+E52+E53+E54+E55 -> 0 | F56: =F48+F49+F50+F51+F52+F53+F54+F55 -> 7750 | G56: =G48+G49+G50+G51+G52+G53+G54+G55 -> 19563.333 | H56: =H48+H49+H50+H51+H52+H53+H54+H55 -> 8763.3333 | I56: =I48+I49+I50+I51+I52+I53+I54+I55 -> 8763.3333 | J56: =J48+J49+J50+J51+J52+J53+J54+J55 -> 14763.333 | ... BJ56: =BJ48+BJ49+BJ50+BJ51+BJ52+BJ53+BJ54+BJ55 -> 18971.398
A57: Memo: imputed unpaid member supervision | C57: =C47*Assumptions!$F$64*C8 -> 0 | D57: =D47*Assumptions!$F$64*D8 -> 0 | E57: =E47*Assumptions!$F$64*E8 -> 0 | F57: =F47*Assumptions!$F$64*F8 -> 3000 | G57: =G47*Assumptions!$F$64*G8 -> 3000 | H57: =H47*Assumptions!$F$64*H8 -> 3000 | I57: =I47*Assumptions!$F$64*I8 -> 3000 | J57: =J47*Assumptions!$F$64*J8 -> 3000 | ... BJ57: =BJ47*Assumptions!$F$64*BJ8 -> 4720.5581
A58: EBITDA excluding grants | C58: =C31-C41+C45-C56 -> 0 | D58: =D31-D41+D45-D56 -> -2000 | E58: =E31-E41+E45-E56 -> 0 | F58: =F31-F41+F45-F56 -> -7750 | G58: =G31-G41+G45-G56 -> -21296.667 | H58: =H31-H41+H45-H56 -> -10496.667 | I58: =I31-I41+I45-I56 -> -10230 | J58: =J31-J41+J45-J56 -> -9340 | ... BJ58: =BJ31-BJ41+BJ45-BJ56 -> -10.490129
A59: INVESTMENT
A60: Capital expenditure | C60: =IF(C$3=Assumptions!$F$7,Assumptions!$F$76+Assumptions!$F$77,0)+IF(AND(Assumptions!$F$9=1,C$3=Assumptions!$F$10-1),(Assumptions!$F$78+Assumptions!$F$79)*C8,0) -> 0 | D60: =IF(D$3=Assumptions!$F$7,Assumptions!$F$76+Assumptions!$F$77,0)+IF(AND(Assumptions!$F$9=1,D$3=Assumptions!$F$10-1),(Assumptions!$F$78+Assumptions!$F$79)*D8,0) -> 0 | E60: =IF(E$3=Assumptions!$F$7,Assumptions!$F$76+Assumptions!$F$77,0)+IF(AND(Assumptions!$F$9=1,E$3=Assumptions!$F$10-1),(Assumptions!$F$78+Assumptions!$F$79)*E8,0) -> 0 | F60: =IF(F$3=Assumptions!$F$7,Assumptions!$F$76+Assumptions!$F$77,0)+IF(AND(Assumptions!$F$9=1,F$3=Assumptions!$F$10-1),(Assumptions!$F$78+Assumptions!$F$79)*F8,0) -> 128000 | G60: =IF(G$3=Assumptions!$F$7,Assumptions!$F$76+Assumptions!$F$77,0)+IF(AND(Assumptions!$F$9=1,G$3=Assumptions!$F$10-1),(Assumptions!$F$78+Assumptions!$F$79)*G8,0) -> 0 | H60: =IF(H$3=Assumptions!$F$7,Assumptions!$F$76+Assumptions!$F$77,0)+IF(AND(Assumptions!$F$9=1,H$3=Assumptions!$F$10-1),(Assumptions!$F$78+Assumptions!$F$79)*H8,0) -> 0 | I60: =IF(I$3=Assumptions!$F$7,Assumptions!$F$76+Assumptions!$F$77,0)+IF(AND(Assumptions!$F$9=1,I$3=Assumptions!$F$10-1),(Assumptions!$F$78+Assumptions!$F$79)*I8,0) -> 0 | J60: =IF(J$3=Assumptions!$F$7,Assumptions!$F$76+Assumptions!$F$77,0)+IF(AND(Assumptions!$F$9=1,J$3=Assumptions!$F$10-1),(Assumptions!$F$78+Assumptions!$F$79)*J8,0) -> 0 | ... BJ60: =IF(BJ$3=Assumptions!$F$7,Assumptions!$F$76+Assumptions!$F$77,0)+IF(AND(Assumptions!$F$9=1,BJ$3=Assumptions!$F$10-1),(Assumptions!$F$78+Assumptions!$F$79)*BJ8,0) -> 0
A61: Of which capital grant | C61: =IF(C$3=Assumptions!$F$7,MIN(Assumptions!$F$80,C60),0) -> 0 | D61: =IF(D$3=Assumptions!$F$7,MIN(Assumptions!$F$80,D60),0) -> 0 | E61: =IF(E$3=Assumptions!$F$7,MIN(Assumptions!$F$80,E60),0) -> 0 | F61: =IF(F$3=Assumptions!$F$7,MIN(Assumptions!$F$80,F60),0) -> 0 | G61: =IF(G$3=Assumptions!$F$7,MIN(Assumptions!$F$80,G60),0) -> 0 | H61: =IF(H$3=Assumptions!$F$7,MIN(Assumptions!$F$80,H60),0) -> 0 | I61: =IF(I$3=Assumptions!$F$7,MIN(Assumptions!$F$80,I60),0) -> 0 | J61: =IF(J$3=Assumptions!$F$7,MIN(Assumptions!$F$80,J60),0) -> 0 | ... BJ61: =IF(BJ$3=Assumptions!$F$7,MIN(Assumptions!$F$80,BJ60),0) -> 0
A62: Depreciation | C62: =IF(C$3>Assumptions!$F$7,Assumptions!$F$76/(Assumptions!$F$81*12)+IF(C$3<=Assumptions!$F$7+Assumptions!$F$82*12,Assumptions!$F$77/(Assumptions!$F$82*12),0),0)+IF(AND(Assumptions!$F$9=1,C$3>Assumptions!$F$10-1),(Assumptions!$F$78/(Assumptions!$F$81*12)+Assumptions!$F$79/(Assumptions!$F$82*12))*(1+Assumptions!$F$41)^(INT((Assumptions!$F$10-2)/12)),0) -> 0 | D62: =IF(D$3>Assumptions!$F$7,Assumptions!$F$76/(Assumptions!$F$81*12)+IF(D$3<=Assumptions!$F$7+Assumptions!$F$82*12,Assumptions!$F$77/(Assumptions!$F$82*12),0),0)+IF(AND(Assumptions!$F$9=1,D$3>Assumptions!$F$10-1),(Assumptions!$F$78/(Assumptions!$F$81*12)+Assumptions!$F$79/(Assumptions!$F$82*12))*(1+Assumptions!$F$41)^(INT((Assumptions!$F$10-2)/12)),0) -> 0 | E62: =IF(E$3>Assumptions!$F$7,Assumptions!$F$76/(Assumptions!$F$81*12)+IF(E$3<=Assumptions!$F$7+Assumptions!$F$82*12,Assumptions!$F$77/(Assumptions!$F$82*12),0),0)+IF(AND(Assumptions!$F$9=1,E$3>Assumptions!$F$10-1),(Assumptions!$F$78/(Assumptions!$F$81*12)+Assumptions!$F$79/(Assumptions!$F$82*12))*(1+Assumptions!$F$41)^(INT((Assumptions!$F$10-2)/12)),0) -> 0 | F62: =IF(F$3>Assumptions!$F$7,Assumptions!$F$76/(Assumptions!$F$81*12)+IF(F$3<=Assumptions!$F$7+Assumptions!$F$82*12,Assumptions!$F$77/(Assumptions!$F$82*12),0),0)+IF(AND(Assumptions!$F$9=1,F$3>Assumptions!$F$10-1),(Assumptions!$F$78/(Assumptions!$F$81*12)+Assumptions!$F$79/(Assumptions!$F$82*12))*(1+Assumptions!$F$41)^(INT((Assumptions!$F$10-2)/12)),0) -> 0 | G62: =IF(G$3>Assumptions!$F$7,Assumptions!$F$76/(Assumptions!$F$81*12)+IF(G$3<=Assumptions!$F$7+Assumptions!$F$82*12,Assumptions!$F$77/(Assumptions!$F$82*12),0),0)+IF(AND(Assumptions!$F$9=1,G$3>Assumptions!$F$10-1),(Assumptions!$F$78/(Assumptions!$F$81*12)+Assumptions!$F$79/(Assumptions!$F$82*12))*(1+Assumptions!$F$41)^(INT((Assumptions!$F$10-2)/12)),0) -> 1216.6667 | H62: =IF(H$3>Assumptions!$F$7,Assumptions!$F$76/(Assumptions!$F$81*12)+IF(H$3<=Assumptions!$F$7+Assumptions!$F$82*12,Assumptions!$F$77/(Assumptions!$F$82*12),0),0)+IF(AND(Assumptions!$F$9=1,H$3>Assumptions!$F$10-1),(Assumptions!$F$78/(Assumptions!$F$81*12)+Assumptions!$F$79/(Assumptions!$F$82*12))*(1+Assumptions!$F$41)^(INT((Assumptions!$F$10-2)/12)),0) -> 1216.6667 | I62: =IF(I$3>Assumptions!$F$7,Assumptions!$F$76/(Assumptions!$F$81*12)+IF(I$3<=Assumptions!$F$7+Assumptions!$F$82*12,Assumptions!$F$77/(Assumptions!$F$82*12),0),0)+IF(AND(Assumptions!$F$9=1,I$3>Assumptions!$F$10-1),(Assumptions!$F$78/(Assumptions!$F$81*12)+Assumptions!$F$79/(Assumptions!$F$82*12))*(1+Assumptions!$F$41)^(INT((Assumptions!$F$10-2)/12)),0) -> 1216.6667 | J62: =IF(J$3>Assumptions!$F$7,Assumptions!$F$76/(Assumptions!$F$81*12)+IF(J$3<=Assumptions!$F$7+Assumptions!$F$82*12,Assumptions!$F$77/(Assumptions!$F$82*12),0),0)+IF(AND(Assumptions!$F$9=1,J$3>Assumptions!$F$10-1),(Assumptions!$F$78/(Assumptions!$F$81*12)+Assumptions!$F$79/(Assumptions!$F$82*12))*(1+Assumptions!$F$41)^(INT((Assumptions!$F$10-2)/12)),0) -> 1216.6667 | ... BJ62: =IF(BJ$3>Assumptions!$F$7,Assumptions!$F$76/(Assumptions!$F$81*12)+IF(BJ$3<=Assumptions!$F$7+Assumptions!$F$82*12,Assumptions!$F$77/(Assumptions!$F$82*12),0),0)+IF(AND(Assumptions!$F$9=1,BJ$3>Assumptions!$F$10-1),(Assumptions!$F$78/(Assumptions!$F$81*12)+Assumptions!$F$79/(Assumptions!$F$82*12))*(1+Assumptions!$F$41)^(INT((Assumptions!$F$10-2)/12)),0) -> 2056.6667
A63: FINANCING
A64: Loan disbursement | C64: =IF(C$3=Assumptions!$F$87,Assumptions!$F$88,0) -> 0 | D64: =IF(D$3=Assumptions!$F$87,Assumptions!$F$88,0) -> 0 | E64: =IF(E$3=Assumptions!$F$87,Assumptions!$F$88,0) -> 120000 | F64: =IF(F$3=Assumptions!$F$87,Assumptions!$F$88,0) -> 0 | G64: =IF(G$3=Assumptions!$F$87,Assumptions!$F$88,0) -> 0 | H64: =IF(H$3=Assumptions!$F$87,Assumptions!$F$88,0) -> 0 | I64: =IF(I$3=Assumptions!$F$87,Assumptions!$F$88,0) -> 0 | J64: =IF(J$3=Assumptions!$F$87,Assumptions!$F$88,0) -> 0 | ... BJ64: =IF(BJ$3=Assumptions!$F$87,Assumptions!$F$88,0) -> 0
A65: Loan opening balance | C65: =0 -> 0 | D65: =C68 -> 0 | E65: =D68 -> 0 | F65: =E68 -> 120000 | G65: =F68 -> 120000 | H65: =G68 -> 120000 | I65: =H68 -> 120000 | J65: =I68 -> 120000 | K65: =J68 -> 120000 | ... BJ65: =BI68 -> 0
A66: Interest (reducing balance) | C66: =C65*Assumptions!$F$89/12 -> 0 | D66: =D65*Assumptions!$F$89/12 -> 0 | E66: =E65*Assumptions!$F$89/12 -> 0 | F66: =F65*Assumptions!$F$89/12 -> 2200 | G66: =G65*Assumptions!$F$89/12 -> 2200 | H66: =H65*Assumptions!$F$89/12 -> 2200 | I66: =I65*Assumptions!$F$89/12 -> 2200 | J66: =J65*Assumptions!$F$89/12 -> 2200 | ... BJ66: =BJ65*Assumptions!$F$89/12 -> 0
A67: Principal repayment | C67: =IF(AND(C$3>Assumptions!$F$87+Assumptions!$F$90,C$3<=Assumptions!$F$87+Assumptions!$F$90+Assumptions!$F$91),MIN(C65,Assumptions!$F$92-C66),0) -> 0 | D67: =IF(AND(D$3>Assumptions!$F$87+Assumptions!$F$90,D$3<=Assumptions!$F$87+Assumptions!$F$90+Assumptions!$F$91),MIN(D65,Assumptions!$F$92-D66),0) -> 0 | E67: =IF(AND(E$3>Assumptions!$F$87+Assumptions!$F$90,E$3<=Assumptions!$F$87+Assumptions!$F$90+Assumptions!$F$91),MIN(E65,Assumptions!$F$92-E66),0) -> 0 | F67: =IF(AND(F$3>Assumptions!$F$87+Assumptions!$F$90,F$3<=Assumptions!$F$87+Assumptions!$F$90+Assumptions!$F$91),MIN(F65,Assumptions!$F$92-F66),0) -> 0 | G67: =IF(AND(G$3>Assumptions!$F$87+Assumptions!$F$90,G$3<=Assumptions!$F$87+Assumptions!$F$90+Assumptions!$F$91),MIN(G65,Assumptions!$F$92-G66),0) -> 0 | H67: =IF(AND(H$3>Assumptions!$F$87+Assumptions!$F$90,H$3<=Assumptions!$F$87+Assumptions!$F$90+Assumptions!$F$91),MIN(H65,Assumptions!$F$92-H66),0) -> 0 | I67: =IF(AND(I$3>Assumptions!$F$87+Assumptions!$F$90,I$3<=Assumptions!$F$87+Assumptions!$F$90+Assumptions!$F$91),MIN(I65,Assumptions!$F$92-I66),0) -> 0 | J67: =IF(AND(J$3>Assumptions!$F$87+Assumptions!$F$90,J$3<=Assumptions!$F$87+Assumptions!$F$90+Assumptions!$F$91),MIN(J65,Assumptions!$F$92-J66),0) -> 0 | ... BJ67: =IF(AND(BJ$3>Assumptions!$F$87+Assumptions!$F$90,BJ$3<=Assumptions!$F$87+Assumptions!$F$90+Assumptions!$F$91),MIN(BJ65,Assumptions!$F$92-BJ66),0) -> 0
A68: Loan closing balance | C68: =C65+C64-C67 -> 0 | D68: =D65+D64-D67 -> 0 | E68: =E65+E64-E67 -> 120000 | F68: =F65+F64-F67 -> 120000 | G68: =G65+G64-G67 -> 120000 | H68: =H65+H64-H67 -> 120000 | I68: =I65+I64-I67 -> 120000 | J68: =J65+J64-J67 -> 120000 | ... BJ68: =BJ65+BJ64-BJ67 -> 0
A69: Member cash equity contributed | C69: =IF(C$3=Assumptions!$F$84,Assumptions!$F$86,0) -> 20000 | D69: =IF(D$3=Assumptions!$F$84,Assumptions!$F$86,0) -> 0 | E69: =IF(E$3=Assumptions!$F$84,Assumptions!$F$86,0) -> 0 | F69: =IF(F$3=Assumptions!$F$84,Assumptions!$F$86,0) -> 0 | G69: =IF(G$3=Assumptions!$F$84,Assumptions!$F$86,0) -> 0 | H69: =IF(H$3=Assumptions!$F$84,Assumptions!$F$86,0) -> 0 | I69: =IF(I$3=Assumptions!$F$84,Assumptions!$F$86,0) -> 0 | J69: =IF(J$3=Assumptions!$F$84,Assumptions!$F$86,0) -> 0 | ... BJ69: =IF(BJ$3=Assumptions!$F$84,Assumptions!$F$86,0) -> 0
A70: PROFIT AND TAX
A71: Profit before tax (incl. grant income) | C71: =C58-C62-C66+C42 -> 0 | D71: =D58-D62-D66+D42 -> -2000 | E71: =E58-E62-E66+E42 -> 0 | F71: =F58-F62-F66+F42 -> -9950 | G71: =G58-G62-G66+G42 -> -24713.333 | H71: =H58-H62-H66+H42 -> -13913.333 | I71: =I58-I62-I66+I42 -> -13646.667 | J71: =J58-J62-J66+J42 -> -12756.667 | ... BJ71: =BJ58-BJ62-BJ66+BJ42 -> -2067.1568
A72: Business income tax paid (prior PY, paid in month 1 of next PY) | C72: =IF(AND(C$3>12,MOD(C$3,12)=1),MAX(0,SUMIF($C$4:$BJ$4,C$4-1,$C$71:$BJ$71))*Assumptions!$F$93,0) -> 0 | D72: =IF(AND(D$3>12,MOD(D$3,12)=1),MAX(0,SUMIF($C$4:$BJ$4,D$4-1,$C$71:$BJ$71))*Assumptions!$F$93,0) -> 0 | E72: =IF(AND(E$3>12,MOD(E$3,12)=1),MAX(0,SUMIF($C$4:$BJ$4,E$4-1,$C$71:$BJ$71))*Assumptions!$F$93,0) -> 0 | F72: =IF(AND(F$3>12,MOD(F$3,12)=1),MAX(0,SUMIF($C$4:$BJ$4,F$4-1,$C$71:$BJ$71))*Assumptions!$F$93,0) -> 0 | G72: =IF(AND(G$3>12,MOD(G$3,12)=1),MAX(0,SUMIF($C$4:$BJ$4,G$4-1,$C$71:$BJ$71))*Assumptions!$F$93,0) -> 0 | H72: =IF(AND(H$3>12,MOD(H$3,12)=1),MAX(0,SUMIF($C$4:$BJ$4,H$4-1,$C$71:$BJ$71))*Assumptions!$F$93,0) -> 0 | I72: =IF(AND(I$3>12,MOD(I$3,12)=1),MAX(0,SUMIF($C$4:$BJ$4,I$4-1,$C$71:$BJ$71))*Assumptions!$F$93,0) -> 0 | J72: =IF(AND(J$3>12,MOD(J$3,12)=1),MAX(0,SUMIF($C$4:$BJ$4,J$4-1,$C$71:$BJ$71))*Assumptions!$F$93,0) -> 0 | ... BJ72: =IF(AND(BJ$3>12,MOD(BJ$3,12)=1),MAX(0,SUMIF($C$4:$BJ$4,BJ$4-1,$C$71:$BJ$71))*Assumptions!$F$93,0) -> 0
A73: CASH FLOW
A74: Operating cash flow | C74: =C32-C43-C56-C66-C72 -> 0 | D74: =D32-D43-D56-D66-D72 -> -2000 | E74: =E32-E43-E56-E66-E72 -> 0 | F74: =F32-F43-F56-F66-F72 -> -9950 | G74: =G32-G43-G56-G66-G72 -> -23496.667 | H74: =H32-H43-H56-H66-H72 -> -12696.667 | I74: =I32-I43-I56-I66-I72 -> -12430 | J74: =J32-J43-J56-J66-J72 -> -14036 | ... BJ74: =BJ32-BJ43-BJ56-BJ66-BJ72 -> -2917.8294
A75: Investing cash flow (cash-funded capex) | C75: =-(C60-C61) -> 0 | D75: =-(D60-D61) -> 0 | E75: =-(E60-E61) -> 0 | F75: =-(F60-F61) -> -128000 | G75: =-(G60-G61) -> 0 | H75: =-(H60-H61) -> 0 | I75: =-(I60-I61) -> 0 | J75: =-(J60-J61) -> 0 | ... BJ75: =-(BJ60-BJ61) -> 0
A76: Financing cash flow | C76: =C69+C64-C67 -> 20000 | D76: =D69+D64-D67 -> 0 | E76: =E69+E64-E67 -> 120000 | F76: =F69+F64-F67 -> 0 | G76: =G69+G64-G67 -> 0 | H76: =H69+H64-H67 -> 0 | I76: =I69+I64-I67 -> 0 | J76: =J69+J64-J67 -> 0 | ... BJ76: =BJ69+BJ64-BJ67 -> 0
A77: Net cash flow | C77: =C74+C75+C76 -> 20000 | D77: =D74+D75+D76 -> -2000 | E77: =E74+E75+E76 -> 120000 | F77: =F74+F75+F76 -> -137950 | G77: =G74+G75+G76 -> -23496.667 | H77: =H74+H75+H76 -> -12696.667 | I77: =I74+I75+I76 -> -12430 | J77: =J74+J75+J76 -> -14036 | ... BJ77: =BJ74+BJ75+BJ76 -> -2917.8294
A78: Opening cash | C78: =0 -> 0 | D78: =C80 -> 20000 | E78: =D80 -> 18000 | F78: =E80 -> 138000 | G78: =F80 -> 5000 | H78: =G80 -> 5000 | I78: =H80 -> 5000 | J78: =I80 -> 5000 | K78: =J80 -> 5000 | ... BJ78: =BI80 -> 207845.44
A79: Additional funding required - source NOT identified (keeps cash at minimum buffer) | C79: =MAX(0,Assumptions!$F$85-(C78+C77)) -> 0 | D79: =MAX(0,Assumptions!$F$85-(D78+D77)) -> 0 | E79: =MAX(0,Assumptions!$F$85-(E78+E77)) -> 0 | F79: =MAX(0,Assumptions!$F$85-(F78+F77)) -> 4950 | G79: =MAX(0,Assumptions!$F$85-(G78+G77)) -> 23496.667 | H79: =MAX(0,Assumptions!$F$85-(H78+H77)) -> 12696.667 | I79: =MAX(0,Assumptions!$F$85-(I78+I77)) -> 12430 | J79: =MAX(0,Assumptions!$F$85-(J78+J77)) -> 14036 | ... BJ79: =MAX(0,Assumptions!$F$85-(BJ78+BJ77)) -> 0
A80: Closing cash | C80: =C78+C77+C79 -> 20000 | D80: =D78+D77+D79 -> 18000 | E80: =E78+E77+E79 -> 138000 | F80: =F78+F77+F79 -> 5000 | G80: =G78+G77+G79 -> 5000 | H80: =H78+H77+H79 -> 5000 | I80: =I78+I77+I79 -> 5000 | J80: =J78+J77+J79 -> 5000 | ... BJ80: =BJ78+BJ77+BJ79 -> 204927.61
A81: Cumulative additional funding required | C81: =C79 -> 0 | D81: =C81+D79 -> 0 | E81: =D81+E79 -> 0 | F81: =E81+F79 -> 4950 | G81: =F81+G79 -> 28446.667 | H81: =G81+H79 -> 41143.333 | I81: =H81+I79 -> 53573.333 | J81: =I81+J79 -> 67609.333 | K81: =J81+K79 -> 73149.333 | ... BJ81: =BI81+BJ79 -> 318974.28
A82: Cumulative capex (gross fixed assets) | C82: =C60 -> 0 | D82: =C82+D60 -> 0 | E82: =D82+E60 -> 0 | F82: =E82+F60 -> 128000 | G82: =F82+G60 -> 128000 | H82: =G82+H60 -> 128000 | I82: =H82+I60 -> 128000 | J82: =I82+J60 -> 128000 | K82: =J82+K60 -> 128000 | ... BJ82: =BI82+BJ60 -> 223200
A83: Accumulated depreciation | C83: =C62 -> 0 | D83: =C83+D62 -> 0 | E83: =D83+E62 -> 0 | F83: =E83+F62 -> 0 | G83: =F83+G62 -> 1216.6667 | H83: =G83+H62 -> 2433.3333 | I83: =H83+I62 -> 3650 | J83: =I83+J62 -> 4866.6667 | K83: =J83+K62 -> 6083.3333 | ... BJ83: =BI83+BJ62 -> 105093.33
A84: Cumulative capital grants / in-kind assets | C84: =C61 -> 0 | D84: =C84+D61 -> 0 | E84: =D84+E61 -> 0 | F84: =E84+F61 -> 0 | G84: =F84+G61 -> 0 | H84: =G84+H61 -> 0 | I84: =H84+I61 -> 0 | J84: =I84+J61 -> 0 | K84: =J84+K61 -> 0 | ... BJ84: =BI84+BJ61 -> 0
A85: Cumulative member equity | C85: =C69 -> 20000 | D85: =C85+D69 -> 20000 | E85: =D85+E69 -> 20000 | F85: =E85+F69 -> 20000 | G85: =F85+G69 -> 20000 | H85: =G85+H69 -> 20000 | I85: =H85+I69 -> 20000 | J85: =I85+J69 -> 20000 | K85: =J85+K69 -> 20000 | ... BJ85: =BI85+BJ69 -> 20000

Sheet Annual
A1: Integrated Vermicompost Unit (proposed new component) - Annual statements, Project Years 1-5 (PY = 12 model months from the Sep. start)
A3: ETB | B3: PY1 | C3: PY2 | D3: PY3 | E3: PY4 | F3: PY5 | G3: Total PY1-5
A4: INCOME STATEMENT
A5: Vermicompost sales | B5: =SUMIF(Monthly!$C$4:$BJ$4,1,Monthly!$C$29:$BJ$29) -> 40213.333 | C5: =SUMIF(Monthly!$C$4:$BJ$4,2,Monthly!$C$29:$BJ$29) -> 209132.37 | D5: =SUMIF(Monthly!$C$4:$BJ$4,3,Monthly!$C$29:$BJ$29) -> 420668.89 | E5: =SUMIF(Monthly!$C$4:$BJ$4,4,Monthly!$C$29:$BJ$29) -> 476911.24 | F5: =SUMIF(Monthly!$C$4:$BJ$4,5,Monthly!$C$29:$BJ$29) -> 534140.59 | G5: =SUM(B5:F5) -> 1681066.4
A6: Earthworm sales | B6: =SUMIF(Monthly!$C$4:$BJ$4,1,Monthly!$C$30:$BJ$30) -> 0 | C6: =SUMIF(Monthly!$C$4:$BJ$4,2,Monthly!$C$30:$BJ$30) -> 11760 | D6: =SUMIF(Monthly!$C$4:$BJ$4,3,Monthly!$C$30:$BJ$30) -> 13171.2 | E6: =SUMIF(Monthly!$C$4:$BJ$4,4,Monthly!$C$30:$BJ$30) -> 14751.744 | F6: =SUMIF(Monthly!$C$4:$BJ$4,5,Monthly!$C$30:$BJ$30) -> 16521.953 | G6: =SUM(B6:F6) -> 56204.897
A7: Total sales revenue | B7: =B5+B6 -> 40213.333 | C7: =C5+C6 -> 220892.37 | D7: =D5+D6 -> 433840.09 | E7: =E5+E6 -> 491662.98 | F7: =F5+F6 -> 550662.54 | G7: =SUM(B7:F7) -> 1737271.3
A8: Poultry litter handling | B8: =SUMIF(Monthly!$C$4:$BJ$4,1,Monthly!$C$35:$BJ$35) -> 400 | C8: =SUMIF(Monthly!$C$4:$BJ$4,2,Monthly!$C$35:$BJ$35) -> 896 | D8: =SUMIF(Monthly!$C$4:$BJ$4,3,Monthly!$C$35:$BJ$35) -> 1003.52 | E8: =SUMIF(Monthly!$C$4:$BJ$4,4,Monthly!$C$35:$BJ$35) -> 1123.9424 | F8: =SUMIF(Monthly!$C$4:$BJ$4,5,Monthly!$C$35:$BJ$35) -> 1258.8155 | G8: =SUM(B8:F8) -> 4682.2779
A9: Other feedstock delivered | B9: =SUMIF(Monthly!$C$4:$BJ$4,1,Monthly!$C$36:$BJ$36) -> 10533.333 | C9: =SUMIF(Monthly!$C$4:$BJ$4,2,Monthly!$C$36:$BJ$36) -> 40021.333 | D9: =SUMIF(Monthly!$C$4:$BJ$4,3,Monthly!$C$36:$BJ$36) -> 63221.76 | E9: =SUMIF(Monthly!$C$4:$BJ$4,4,Monthly!$C$36:$BJ$36) -> 70808.371 | F9: =SUMIF(Monthly!$C$4:$BJ$4,5,Monthly!$C$36:$BJ$36) -> 79305.376 | G9: =SUM(B9:F9) -> 263890.17
A10: Casual labour - feedstock handling | B10: =SUMIF(Monthly!$C$4:$BJ$4,1,Monthly!$C$37:$BJ$37) -> 3760 | C10: =SUMIF(Monthly!$C$4:$BJ$4,2,Monthly!$C$37:$BJ$37) -> 13350.4 | D10: =SUMIF(Monthly!$C$4:$BJ$4,3,Monthly!$C$37:$BJ$37) -> 20471.808 | E10: =SUMIF(Monthly!$C$4:$BJ$4,4,Monthly!$C$37:$BJ$37) -> 22928.425 | F10: =SUMIF(Monthly!$C$4:$BJ$4,5,Monthly!$C$37:$BJ$37) -> 25679.836 | G10: =SUM(B10:F10) -> 86190.469
A11: Casual labour - harvest and screening | B11: =SUMIF(Monthly!$C$4:$BJ$4,1,Monthly!$C$38:$BJ$38) -> 1950 | C11: =SUMIF(Monthly!$C$4:$BJ$4,2,Monthly!$C$38:$BJ$38) -> 10788.96 | D11: =SUMIF(Monthly!$C$4:$BJ$4,3,Monthly!$C$38:$BJ$38) -> 19617.562 | E11: =SUMIF(Monthly!$C$4:$BJ$4,4,Monthly!$C$38:$BJ$38) -> 22355.214 | F11: =SUMIF(Monthly!$C$4:$BJ$4,5,Monthly!$C$38:$BJ$38) -> 25037.84 | G11: =SUM(B11:F11) -> 79749.576
A12: Bags and labels | B12: =SUMIF(Monthly!$C$4:$BJ$4,1,Monthly!$C$39:$BJ$39) -> 3016 | C12: =SUMIF(Monthly!$C$4:$BJ$4,2,Monthly!$C$39:$BJ$39) -> 15684.928 | D12: =SUMIF(Monthly!$C$4:$BJ$4,3,Monthly!$C$39:$BJ$39) -> 31550.167 | E12: =SUMIF(Monthly!$C$4:$BJ$4,4,Monthly!$C$39:$BJ$39) -> 35768.343 | F12: =SUMIF(Monthly!$C$4:$BJ$4,5,Monthly!$C$39:$BJ$39) -> 40060.544 | G12: =SUM(B12:F12) -> 126079.98
A13: Delivery | B13: =SUMIF(Monthly!$C$4:$BJ$4,1,Monthly!$C$40:$BJ$40) -> 2010.6667 | C13: =SUMIF(Monthly!$C$4:$BJ$4,2,Monthly!$C$40:$BJ$40) -> 10456.619 | D13: =SUMIF(Monthly!$C$4:$BJ$4,3,Monthly!$C$40:$BJ$40) -> 21033.445 | E13: =SUMIF(Monthly!$C$4:$BJ$4,4,Monthly!$C$40:$BJ$40) -> 23845.562 | F13: =SUMIF(Monthly!$C$4:$BJ$4,5,Monthly!$C$40:$BJ$40) -> 26707.029 | G13: =SUM(B13:F13) -> 84053.321
A14: Total variable (direct) costs | B14: =B8+B9+B10+B11+B12+B13 -> 21670 | C14: =C8+C9+C10+C11+C12+C13 -> 91198.24 | D14: =D8+D9+D10+D11+D12+D13 -> 156898.26 | E14: =E8+E9+E10+E11+E12+E13 -> 176829.86 | F14: =F8+F9+F10+F11+F12+F13 -> 198049.44 | G14: =SUM(B14:F14) -> 644645.8
A15: Less: increase in finished-goods inventory (at standard cost) | B15: =SUMIF(Monthly!$C$4:$BJ$4,1,Monthly!$C$45:$BJ$45) -> 353.88889 | C15: =SUMIF(Monthly!$C$4:$BJ$4,2,Monthly!$C$45:$BJ$45) -> 5410.0356 | D15: =SUMIF(Monthly!$C$4:$BJ$4,3,Monthly!$C$45:$BJ$45) -> 140.18791 | E15: =SUMIF(Monthly!$C$4:$BJ$4,4,Monthly!$C$45:$BJ$45) -> 708.49348 | F15: =SUMIF(Monthly!$C$4:$BJ$4,5,Monthly!$C$45:$BJ$45) -> 793.5127 | G15: =SUM(B15:F15) -> 7406.1185
A16: Gross margin | B16: =B7-B14+B15 -> 18897.222 | C16: =C7-C14+C15 -> 135104.17 | D16: =D7-D14+D15 -> 277082.02 | E16: =E7-E14+E15 -> 315541.62 | F16: =F7-F14+F15 -> 353406.61 | G16: =SUM(B16:F16) -> 1100031.6
A17: Gross margin % | B17: =IF(B7=0,0,B16/B7) -> 0.46992429 | C17: =IF(C7=0,0,C16/C7) -> 0.61162894 | D17: =IF(D7=0,0,D16/D7) -> 0.63867315 | E17: =IF(E7=0,0,E16/E7) -> 0.64178437 | F17: =IF(F7=0,0,F16/F7) -> 0.64178437
A18: Paid member-workers | B18: =SUMIF(Monthly!$C$4:$BJ$4,1,Monthly!$C$48:$BJ$48) -> 54000 | C18: =SUMIF(Monthly!$C$4:$BJ$4,2,Monthly!$C$48:$BJ$48) -> 107520 | D18: =SUMIF(Monthly!$C$4:$BJ$4,3,Monthly!$C$48:$BJ$48) -> 135475.2 | E18: =SUMIF(Monthly!$C$4:$BJ$4,4,Monthly!$C$48:$BJ$48) -> 151732.22 | F18: =SUMIF(Monthly!$C$4:$BJ$4,5,Monthly!$C$48:$BJ$48) -> 169940.09 | G18: =SUM(B18:F18) -> 618667.51
A19: Water | B19: =SUMIF(Monthly!$C$4:$BJ$4,1,Monthly!$C$49:$BJ$49) -> 3840 | C19: =SUMIF(Monthly!$C$4:$BJ$4,2,Monthly!$C$49:$BJ$49) -> 10752 | D19: =SUMIF(Monthly!$C$4:$BJ$4,3,Monthly!$C$49:$BJ$49) -> 14450.688 | E19: =SUMIF(Monthly!$C$4:$BJ$4,4,Monthly!$C$49:$BJ$49) -> 16184.771 | F19: =SUMIF(Monthly!$C$4:$BJ$4,5,Monthly!$C$49:$BJ$49) -> 18126.943 | G19: =SUM(B19:F19) -> 63354.402
A20: Laboratory testing | B20: =SUMIF(Monthly!$C$4:$BJ$4,1,Monthly!$C$50:$BJ$50) -> 6000 | C20: =SUMIF(Monthly!$C$4:$BJ$4,2,Monthly!$C$50:$BJ$50) -> 13440 | D20: =SUMIF(Monthly!$C$4:$BJ$4,3,Monthly!$C$50:$BJ$50) -> 15052.8 | E20: =SUMIF(Monthly!$C$4:$BJ$4,4,Monthly!$C$50:$BJ$50) -> 16859.136 | F20: =SUMIF(Monthly!$C$4:$BJ$4,5,Monthly!$C$50:$BJ$50) -> 18882.232 | G20: =SUM(B20:F20) -> 70234.168
A21: Marketing and demonstrations | B21: =SUMIF(Monthly!$C$4:$BJ$4,1,Monthly!$C$51:$BJ$51) -> 11250 | C21: =SUMIF(Monthly!$C$4:$BJ$4,2,Monthly!$C$51:$BJ$51) -> 8960 | D21: =SUMIF(Monthly!$C$4:$BJ$4,3,Monthly!$C$51:$BJ$51) -> 10035.2 | E21: =SUMIF(Monthly!$C$4:$BJ$4,4,Monthly!$C$51:$BJ$51) -> 11239.424 | F21: =SUMIF(Monthly!$C$4:$BJ$4,5,Monthly!$C$51:$BJ$51) -> 12588.155 | G21: =SUM(B21:F21) -> 54072.779
A22: Administration | B22: =SUMIF(Monthly!$C$4:$BJ$4,1,Monthly!$C$52:$BJ$52) -> 4500 | C22: =SUMIF(Monthly!$C$4:$BJ$4,2,Monthly!$C$52:$BJ$52) -> 6720 | D22: =SUMIF(Monthly!$C$4:$BJ$4,3,Monthly!$C$52:$BJ$52) -> 7526.4 | E22: =SUMIF(Monthly!$C$4:$BJ$4,4,Monthly!$C$52:$BJ$52) -> 8429.568 | F22: =SUMIF(Monthly!$C$4:$BJ$4,5,Monthly!$C$52:$BJ$52) -> 9441.1162 | G22: =SUM(B22:F22) -> 36617.084
A23: Maintenance | B23: =SUMIF(Monthly!$C$4:$BJ$4,1,Monthly!$C$53:$BJ$53) -> 4266.6667 | C23: =SUMIF(Monthly!$C$4:$BJ$4,2,Monthly!$C$53:$BJ$53) -> 10722.133 | D23: =SUMIF(Monthly!$C$4:$BJ$4,3,Monthly!$C$53:$BJ$53) -> 13999.104 | E23: =SUMIF(Monthly!$C$4:$BJ$4,4,Monthly!$C$53:$BJ$53) -> 15678.996 | F23: =SUMIF(Monthly!$C$4:$BJ$4,5,Monthly!$C$53:$BJ$53) -> 17560.476 | G23: =SUM(B23:F23) -> 62227.377
A24: Registration and licences | B24: =SUMIF(Monthly!$C$4:$BJ$4,1,Monthly!$C$54:$BJ$54) -> 2000 | C24: =SUMIF(Monthly!$C$4:$BJ$4,2,Monthly!$C$54:$BJ$54) -> 1680 | D24: =SUMIF(Monthly!$C$4:$BJ$4,3,Monthly!$C$54:$BJ$54) -> 1881.6 | E24: =SUMIF(Monthly!$C$4:$BJ$4,4,Monthly!$C$54:$BJ$54) -> 2107.392 | F24: =SUMIF(Monthly!$C$4:$BJ$4,5,Monthly!$C$54:$BJ$54) -> 2360.279 | G24: =SUM(B24:F24) -> 10029.271
A25: Starter earthworms (pre-operating) | B25: =SUMIF(Monthly!$C$4:$BJ$4,1,Monthly!$C$55:$BJ$55) -> 10800 | C25: =SUMIF(Monthly!$C$4:$BJ$4,2,Monthly!$C$55:$BJ$55) -> 0 | D25: =SUMIF(Monthly!$C$4:$BJ$4,3,Monthly!$C$55:$BJ$55) -> 0 | E25: =SUMIF(Monthly!$C$4:$BJ$4,4,Monthly!$C$55:$BJ$55) -> 0 | F25: =SUMIF(Monthly!$C$4:$BJ$4,5,Monthly!$C$55:$BJ$55) -> 0 | G25: =SUM(B25:F25) -> 10800
A26: Total fixed operating costs | B26: =B18+B19+B20+B21+B22+B23+B24+B25 -> 96656.667 | C26: =C18+C19+C20+C21+C22+C23+C24+C25 -> 159794.13 | D26: =D18+D19+D20+D21+D22+D23+D24+D25 -> 198420.99 | E26: =E18+E19+E20+E21+E22+E23+E24+E25 -> 222231.51 | F26: =F18+F19+F20+F21+F22+F23+F24+F25 -> 248899.29 | G26: =SUM(B26:F26) -> 926002.6
A27: EBITDA excluding grants | B27: =B16-B26 -> -77759.444 | C27: =C16-C26 -> -24689.964 | D27: =D16-D26 -> 78661.028 | E27: =E16-E26 -> 93310.108 | F27: =F16-F26 -> 104507.32 | G27: =SUM(B27:F27) -> 174029.05
A28: Depreciation | B28: =SUMIF(Monthly!$C$4:$BJ$4,1,Monthly!$C$62:$BJ$62) -> 9733.3333 | C28: =SUMIF(Monthly!$C$4:$BJ$4,2,Monthly!$C$62:$BJ$62) -> 21320 | D28: =SUMIF(Monthly!$C$4:$BJ$4,3,Monthly!$C$62:$BJ$62) -> 24680 | E28: =SUMIF(Monthly!$C$4:$BJ$4,4,Monthly!$C$62:$BJ$62) -> 24680 | F28: =SUMIF(Monthly!$C$4:$BJ$4,5,Monthly!$C$62:$BJ$62) -> 24680 | G28: =SUM(B28:F28) -> 105093.33
A29: Operating profit (EBIT) excluding grants | B29: =B27-B28 -> -87492.778 | C29: =C27-C28 -> -46009.964 | D29: =D27-D28 -> 53981.028 | E29: =E27-E28 -> 68630.108 | F29: =F27-F28 -> 79827.321 | G29: =SUM(B29:F29) -> 68935.715
A30: Interest expense | B30: =SUMIF(Monthly!$C$4:$BJ$4,1,Monthly!$C$66:$BJ$66) -> 19668.142 | C30: =SUMIF(Monthly!$C$4:$BJ$4,2,Monthly!$C$66:$BJ$66) -> 21559.576 | D30: =SUMIF(Monthly!$C$4:$BJ$4,3,Monthly!$C$66:$BJ$66) -> 13415.003 | E30: =SUMIF(Monthly!$C$4:$BJ$4,4,Monthly!$C$66:$BJ$66) -> 3540.0372 | F30: =SUMIF(Monthly!$C$4:$BJ$4,5,Monthly!$C$66:$BJ$66) -> 0 | G30: =SUM(B30:F30) -> 58182.758
A31: Profit before grants and tax | B31: =B29-B30 -> -107160.92 | C31: =C29-C30 -> -67569.54 | D31: =D29-D30 -> 40566.026 | E31: =E29-E30 -> 65090.071 | F31: =F29-F30 -> 79827.321 | G31: =SUM(B31:F31) -> 10752.957
A32: Grant income - in-kind inputs (non-cash, non-recurring) | B32: =SUMIF(Monthly!$C$4:$BJ$4,1,Monthly!$C$42:$BJ$42) -> 0 | C32: =SUMIF(Monthly!$C$4:$BJ$4,2,Monthly!$C$42:$BJ$42) -> 0 | D32: =SUMIF(Monthly!$C$4:$BJ$4,3,Monthly!$C$42:$BJ$42) -> 0 | E32: =SUMIF(Monthly!$C$4:$BJ$4,4,Monthly!$C$42:$BJ$42) -> 0 | F32: =SUMIF(Monthly!$C$4:$BJ$4,5,Monthly!$C$42:$BJ$42) -> 0 | G32: =SUM(B32:F32) -> 0
A33: Profit before tax | B33: =B31+B32 -> -107160.92 | C33: =C31+C32 -> -67569.54 | D33: =D31+D32 -> 40566.026 | E33: =E31+E32 -> 65090.071 | F33: =F31+F32 -> 79827.321 | G33: =SUM(B33:F33) -> 10752.957
A34: Business income tax (placeholder rate; to verify) | B34: =MAX(0,B33)*Assumptions!$F$93 -> 0 | C34: =MAX(0,C33)*Assumptions!$F$93 -> 0 | D34: =MAX(0,D33)*Assumptions!$F$93 -> 4056.6026 | E34: =MAX(0,E33)*Assumptions!$F$93 -> 6509.0071 | F34: =MAX(0,F33)*Assumptions!$F$93 -> 7982.7321 | G34: =SUM(B34:F34) -> 18548.342
A35: NET PROFIT | B35: =B33-B34 -> -107160.92 | C35: =C33-C34 -> -67569.54 | D35: =D33-D34 -> 36509.423 | E35: =E33-E34 -> 58581.064 | F35: =F33-F34 -> 71844.589 | G35: =SUM(B35:F35) -> -7795.3846
A36: Memo: net profit excluding grant income | B36: =B35-B32 -> -107160.92 | C36: =C35-C32 -> -67569.54 | D36: =D35-D32 -> 36509.423 | E36: =E35-E32 -> 58581.064 | F36: =F35-F32 -> 71844.589 | G36: =SUM(B36:F36) -> -7795.3846
A37: Memo: imputed value of unpaid member labour | B37: =SUMIF(Monthly!$C$4:$BJ$4,1,Monthly!$C$57:$BJ$57) -> 27000 | C37: =SUMIF(Monthly!$C$4:$BJ$4,2,Monthly!$C$57:$BJ$57) -> 40320 | D37: =SUMIF(Monthly!$C$4:$BJ$4,3,Monthly!$C$57:$BJ$57) -> 45158.4 | E37: =SUMIF(Monthly!$C$4:$BJ$4,4,Monthly!$C$57:$BJ$57) -> 50577.408 | F37: =SUMIF(Monthly!$C$4:$BJ$4,5,Monthly!$C$57:$BJ$57) -> 56646.697 | G37: =SUM(B37:F37) -> 219702.5
A38: Memo: economic profit after imputing unpaid labour, excl. grants | B38: =B36-B37 -> -134160.92 | C38: =C36-C37 -> -107889.54 | D38: =D36-D37 -> -8648.9769 | E38: =E36-E37 -> 8003.6556 | F38: =F36-F37 -> 15197.892 | G38: =SUM(B38:F38) -> -227497.89
A40: CASH FLOW STATEMENT (direct method)
A41: Cash collected from customers | B41: =SUMIF(Monthly!$C$4:$BJ$4,1,Monthly!$C$32:$BJ$32) -> 38101.333 | C41: =SUMIF(Monthly!$C$4:$BJ$4,2,Monthly!$C$32:$BJ$32) -> 218570.85 | D41: =SUMIF(Monthly!$C$4:$BJ$4,3,Monthly!$C$32:$BJ$32) -> 431321.1 | E41: =SUMIF(Monthly!$C$4:$BJ$4,4,Monthly!$C$32:$BJ$32) -> 490828.68 | F41: =SUMIF(Monthly!$C$4:$BJ$4,5,Monthly!$C$32:$BJ$32) -> 549728.12 | G41: =SUM(B41:F41) -> 1728550.1
A42: Cash paid: variable costs (net of in-kind grant inputs) | B42: =SUMIF(Monthly!$C$4:$BJ$4,1,Monthly!$C$43:$BJ$43) -> 21670 | C42: =SUMIF(Monthly!$C$4:$BJ$4,2,Monthly!$C$43:$BJ$43) -> 91198.24 | D42: =SUMIF(Monthly!$C$4:$BJ$4,3,Monthly!$C$43:$BJ$43) -> 156898.26 | E42: =SUMIF(Monthly!$C$4:$BJ$4,4,Monthly!$C$43:$BJ$43) -> 176829.86 | F42: =SUMIF(Monthly!$C$4:$BJ$4,5,Monthly!$C$43:$BJ$43) -> 198049.44 | G42: =SUM(B42:F42) -> 644645.8
A43: Cash paid: fixed operating costs | B43: =SUMIF(Monthly!$C$4:$BJ$4,1,Monthly!$C$56:$BJ$56) -> 96656.667 | C43: =SUMIF(Monthly!$C$4:$BJ$4,2,Monthly!$C$56:$BJ$56) -> 159794.13 | D43: =SUMIF(Monthly!$C$4:$BJ$4,3,Monthly!$C$56:$BJ$56) -> 198420.99 | E43: =SUMIF(Monthly!$C$4:$BJ$4,4,Monthly!$C$56:$BJ$56) -> 222231.51 | F43: =SUMIF(Monthly!$C$4:$BJ$4,5,Monthly!$C$56:$BJ$56) -> 248899.29 | G43: =SUM(B43:F43) -> 926002.6
A44: Interest paid | B44: =SUMIF(Monthly!$C$4:$BJ$4,1,Monthly!$C$66:$BJ$66) -> 19668.142 | C44: =SUMIF(Monthly!$C$4:$BJ$4,2,Monthly!$C$66:$BJ$66) -> 21559.576 | D44: =SUMIF(Monthly!$C$4:$BJ$4,3,Monthly!$C$66:$BJ$66) -> 13415.003 | E44: =SUMIF(Monthly!$C$4:$BJ$4,4,Monthly!$C$66:$BJ$66) -> 3540.0372 | F44: =SUMIF(Monthly!$C$4:$BJ$4,5,Monthly!$C$66:$BJ$66) -> 0 | G44: =SUM(B44:F44) -> 58182.758
A45: Income tax paid | B45: =SUMIF(Monthly!$C$4:$BJ$4,1,Monthly!$C$72:$BJ$72) -> 0 | C45: =SUMIF(Monthly!$C$4:$BJ$4,2,Monthly!$C$72:$BJ$72) -> 0 | D45: =SUMIF(Monthly!$C$4:$BJ$4,3,Monthly!$C$72:$BJ$72) -> 0 | E45: =SUMIF(Monthly!$C$4:$BJ$4,4,Monthly!$C$72:$BJ$72) -> 4056.6026 | F45: =SUMIF(Monthly!$C$4:$BJ$4,5,Monthly!$C$72:$BJ$72) -> 6509.0071 | G45: =SUM(B45:F45) -> 10565.61
A46: Net cash from operations | B46: =B41-B42-B43-B44-B45 -> -99893.475 | C46: =C41-C42-C43-C44-C45 -> -53981.096 | D46: =D41-D42-D43-D44-D45 -> 62586.846 | E46: =E41-E42-E43-E44-E45 -> 84170.673 | F46: =F41-F42-F43-F44-F45 -> 96270.383 | G46: =SUM(B46:F46) -> 89153.331
A47: Net cash from investing (cash-funded capex) | B47: =SUMIF(Monthly!$C$4:$BJ$4,1,Monthly!$C$75:$BJ$75) -> -128000 | C47: =SUMIF(Monthly!$C$4:$BJ$4,2,Monthly!$C$75:$BJ$75) -> -95200 | D47: =SUMIF(Monthly!$C$4:$BJ$4,3,Monthly!$C$75:$BJ$75) -> 0 | E47: =SUMIF(Monthly!$C$4:$BJ$4,4,Monthly!$C$75:$BJ$75) -> 0 | F47: =SUMIF(Monthly!$C$4:$BJ$4,5,Monthly!$C$75:$BJ$75) -> 0 | G47: =SUM(B47:F47) -> -223200
A48: Member equity received | B48: =SUMIF(Monthly!$C$4:$BJ$4,1,Monthly!$C$69:$BJ$69) -> 20000 | C48: =SUMIF(Monthly!$C$4:$BJ$4,2,Monthly!$C$69:$BJ$69) -> 0 | D48: =SUMIF(Monthly!$C$4:$BJ$4,3,Monthly!$C$69:$BJ$69) -> 0 | E48: =SUMIF(Monthly!$C$4:$BJ$4,4,Monthly!$C$69:$BJ$69) -> 0 | F48: =SUMIF(Monthly!$C$4:$BJ$4,5,Monthly!$C$69:$BJ$69) -> 0 | G48: =SUM(B48:F48) -> 20000
A49: Loan disbursed | B49: =SUMIF(Monthly!$C$4:$BJ$4,1,Monthly!$C$64:$BJ$64) -> 120000 | C49: =SUMIF(Monthly!$C$4:$BJ$4,2,Monthly!$C$64:$BJ$64) -> 0 | D49: =SUMIF(Monthly!$C$4:$BJ$4,3,Monthly!$C$64:$BJ$64) -> 0 | E49: =SUMIF(Monthly!$C$4:$BJ$4,4,Monthly!$C$64:$BJ$64) -> 0 | F49: =SUMIF(Monthly!$C$4:$BJ$4,5,Monthly!$C$64:$BJ$64) -> 0 | G49: =SUM(B49:F49) -> 120000
A50: Loan principal repaid | B50: =SUMIF(Monthly!$C$4:$BJ$4,1,Monthly!$C$67:$BJ$67) -> 7280.421 | C50: =SUMIF(Monthly!$C$4:$BJ$4,2,Monthly!$C$67:$BJ$67) -> 33434.677 | D50: =SUMIF(Monthly!$C$4:$BJ$4,3,Monthly!$C$67:$BJ$67) -> 41579.25 | E50: =SUMIF(Monthly!$C$4:$BJ$4,4,Monthly!$C$67:$BJ$67) -> 37705.652 | F50: =SUMIF(Monthly!$C$4:$BJ$4,5,Monthly!$C$67:$BJ$67) -> 0 | G50: =SUM(B50:F50) -> 120000
A51: Additional funding required (source not identified) | B51: =SUMIF(Monthly!$C$4:$BJ$4,1,Monthly!$C$79:$BJ$79) -> 100173.9 | C51: =SUMIF(Monthly!$C$4:$BJ$4,2,Monthly!$C$79:$BJ$79) -> 182615.77 | D51: =SUMIF(Monthly!$C$4:$BJ$4,3,Monthly!$C$79:$BJ$79) -> 36184.613 | E51: =SUMIF(Monthly!$C$4:$BJ$4,4,Monthly!$C$79:$BJ$79) -> 0 | F51: =SUMIF(Monthly!$C$4:$BJ$4,5,Monthly!$C$79:$BJ$79) -> 0 | G51: =SUM(B51:F51) -> 318974.28
A52: Net cash from financing | B52: =B48+B49-B50+B51 -> 232893.48 | C52: =C48+C49-C50+C51 -> 149181.1 | D52: =D48+D49-D50+D51 -> -5394.6365 | E52: =E48+E49-E50+E51 -> -37705.652 | F52: =F48+F49-F50+F51 -> 0 | G52: =SUM(B52:F52) -> 338974.28
A53: Net change in cash | B53: =B46+B47+B52 -> 5000 | C53: =C46+C47+C52 -> 0 | D53: =D46+D47+D52 -> 57192.209 | E53: =E46+E47+E52 -> 46465.021 | F53: =F46+F47+F52 -> 96270.383 | G53: =SUM(B53:F53) -> 204927.61
A54: Closing cash balance | B54: =INDEX(Monthly!$C$80:$BJ$80,1,12) -> 5000 | C54: =INDEX(Monthly!$C$80:$BJ$80,1,24) -> 5000 | D54: =INDEX(Monthly!$C$80:$BJ$80,1,36) -> 62192.209 | E54: =INDEX(Monthly!$C$80:$BJ$80,1,48) -> 108657.23 | F54: =INDEX(Monthly!$C$80:$BJ$80,1,60) -> 204927.61
A55: Opening cash balance | B55: =0 -> 0 | C55: =B54 -> 5000 | D55: =C54 -> 5000 | E55: =D54 -> 62192.209 | F55: =E54 -> 108657.23
A56: Check: opening + net change - closing (should be 0) | B56: =ROUND(B55+B53-B54,2) -> 0 | C56: =ROUND(C55+C53-C54,2) -> 0 | D56: =ROUND(D55+D53-D54,2) -> 0 | E56: =ROUND(E55+E53-E54,2) -> 0 | F56: =ROUND(F55+F53-F54,2) -> 0
A57: Lowest month-end cash in the year | B57: =MIN(INDEX(Monthly!$C$80:$BJ$80,1,(1-1)*12+1):INDEX(Monthly!$C$80:$BJ$80,1,1*12)) -> 5000 | C57: =MIN(INDEX(Monthly!$C$80:$BJ$80,1,(2-1)*12+1):INDEX(Monthly!$C$80:$BJ$80,1,2*12)) -> 5000 | D57: =MIN(INDEX(Monthly!$C$80:$BJ$80,1,(3-1)*12+1):INDEX(Monthly!$C$80:$BJ$80,1,3*12)) -> 5000 | E57: =MIN(INDEX(Monthly!$C$80:$BJ$80,1,(4-1)*12+1):INDEX(Monthly!$C$80:$BJ$80,1,4*12)) -> 21412.034 | F57: =MIN(INDEX(Monthly!$C$80:$BJ$80,1,(5-1)*12+1):INDEX(Monthly!$C$80:$BJ$80,1,5*12)) -> 79158.834
A59: BALANCE SHEET (end of project year)
A60: Cash | B60: =B54 -> 5000 | C60: =C54 -> 5000 | D60: =D54 -> 62192.209 | E60: =E54 -> 108657.23 | F60: =F54 -> 204927.61
A61: Trade receivables | B61: =INDEX(Monthly!$C$33:$BJ$33,1,12) -> 2112 | C61: =INDEX(Monthly!$C$33:$BJ$33,1,24) -> 4433.52 | D61: =INDEX(Monthly!$C$33:$BJ$33,1,36) -> 6952.512 | E61: =INDEX(Monthly!$C$33:$BJ$33,1,48) -> 7786.8134 | F61: =INDEX(Monthly!$C$33:$BJ$33,1,60) -> 8721.2311
A62: Finished-goods inventory (standard cost) | B62: =INDEX(Monthly!$C$44:$BJ$44,1,12) -> 353.88889 | C62: =INDEX(Monthly!$C$44:$BJ$44,1,24) -> 5763.9244 | D62: =INDEX(Monthly!$C$44:$BJ$44,1,36) -> 5904.1124 | E62: =INDEX(Monthly!$C$44:$BJ$44,1,48) -> 6612.6058 | F62: =INDEX(Monthly!$C$44:$BJ$44,1,60) -> 7406.1185
A63: Fixed assets at cost (incl. in-kind) | B63: =INDEX(Monthly!$C$82:$BJ$82,1,12) -> 128000 | C63: =INDEX(Monthly!$C$82:$BJ$82,1,24) -> 223200 | D63: =INDEX(Monthly!$C$82:$BJ$82,1,36) -> 223200 | E63: =INDEX(Monthly!$C$82:$BJ$82,1,48) -> 223200 | F63: =INDEX(Monthly!$C$82:$BJ$82,1,60) -> 223200
A64: Less accumulated depreciation | B64: =INDEX(Monthly!$C$83:$BJ$83,1,12) -> 9733.3333 | C64: =INDEX(Monthly!$C$83:$BJ$83,1,24) -> 31053.333 | D64: =INDEX(Monthly!$C$83:$BJ$83,1,36) -> 55733.333 | E64: =INDEX(Monthly!$C$83:$BJ$83,1,48) -> 80413.333 | F64: =INDEX(Monthly!$C$83:$BJ$83,1,60) -> 105093.33
A65: Net fixed assets | B65: =B63-B64 -> 118266.67 | C65: =C63-C64 -> 192146.67 | D65: =D63-D64 -> 167466.67 | E65: =E63-E64 -> 142786.67 | F65: =F63-F64 -> 118106.67
A66: TOTAL ASSETS | B66: =B60+B61+B65+B62 -> 125732.56 | C66: =C60+C61+C65+C62 -> 207344.11 | D66: =D60+D61+D65+D62 -> 242515.5 | E66: =E60+E61+E65+E62 -> 265843.32 | F66: =F60+F61+F65+F62 -> 339161.63
A67: Loan outstanding | B67: =INDEX(Monthly!$C$68:$BJ$68,1,12) -> 112719.58 | C67: =INDEX(Monthly!$C$68:$BJ$68,1,24) -> 79284.902 | D67: =INDEX(Monthly!$C$68:$BJ$68,1,36) -> 37705.652 | E67: =INDEX(Monthly!$C$68:$BJ$68,1,48) -> 0 | F67: =INDEX(Monthly!$C$68:$BJ$68,1,60) -> 0
A68: Income tax payable | B68: =B34 -> 0 | C68: =C34 -> 0 | D68: =D34 -> 4056.6026 | E68: =E34 -> 6509.0071 | F68: =F34 -> 7982.7321
A69: Total liabilities | B69: =B67+B68 -> 112719.58 | C69: =C67+C68 -> 79284.902 | D69: =D67+D68 -> 41762.255 | E69: =E67+E68 -> 6509.0071 | F69: =F67+F68 -> 7982.7321
A70: Member paid-in capital | B70: =INDEX(Monthly!$C$85:$BJ$85,1,12) -> 20000 | C70: =INDEX(Monthly!$C$85:$BJ$85,1,24) -> 20000 | D70: =INDEX(Monthly!$C$85:$BJ$85,1,36) -> 20000 | E70: =INDEX(Monthly!$C$85:$BJ$85,1,48) -> 20000 | F70: =INDEX(Monthly!$C$85:$BJ$85,1,60) -> 20000
A71: Contributed capital (capital grants and in-kind assets) | B71: =INDEX(Monthly!$C$84:$BJ$84,1,12) -> 0 | C71: =INDEX(Monthly!$C$84:$BJ$84,1,24) -> 0 | D71: =INDEX(Monthly!$C$84:$BJ$84,1,36) -> 0 | E71: =INDEX(Monthly!$C$84:$BJ$84,1,48) -> 0 | F71: =INDEX(Monthly!$C$84:$BJ$84,1,60) -> 0
A72: Additional funding required, cumulative (source not identified) | B72: =INDEX(Monthly!$C$81:$BJ$81,1,12) -> 100173.9 | C72: =INDEX(Monthly!$C$81:$BJ$81,1,24) -> 282789.67 | D72: =INDEX(Monthly!$C$81:$BJ$81,1,36) -> 318974.28 | E72: =INDEX(Monthly!$C$81:$BJ$81,1,48) -> 318974.28 | F72: =INDEX(Monthly!$C$81:$BJ$81,1,60) -> 318974.28
A73: Retained earnings (no distributions assumed) | B73: =0+B35 -> -107160.92 | C73: =B73+C35 -> -174730.46 | D73: =C73+D35 -> -138221.04 | E73: =D73+E35 -> -79639.973 | F73: =E73+F35 -> -7795.3846
A74: Total equity | B74: =B70+B71+B72+B73 -> 13012.977 | C74: =C70+C71+C72+C73 -> 128059.21 | D74: =D70+D71+D72+D73 -> 200753.25 | E74: =E70+E71+E72+E73 -> 259334.31 | F74: =F70+F71+F72+F73 -> 331178.9
A75: TOTAL LIABILITIES AND EQUITY | B75: =B69+B74 -> 125732.56 | C75: =C69+C74 -> 207344.11 | D75: =D69+D74 -> 242515.5 | E75: =E69+E74 -> 265843.32 | F75: =F69+F74 -> 339161.63
A76: Balance check: assets - (liabilities + equity) (should be 0) | B76: =ROUND(B66-B75,2) -> 0 | C76: =ROUND(C66-C75,2) -> 0 | D76: =ROUND(D66-D75,2) -> 0 | E76: =ROUND(E66-E75,2) -> 0 | F76: =ROUND(F66-F75,2) -> 0
A78: KEY RATIOS
A79: Debt service (interest + principal) | B79: =B30+B50 -> 26948.563 | C79: =C30+C50 -> 54994.253 | D79: =D30+D50 -> 54994.253 | E79: =E30+E50 -> 41245.689 | F79: =F30+F50 -> 0 | G79: =SUM(B79:F79) -> 178182.76
A80: Debt-service coverage ratio = (EBITDA excl. grants - tax paid) / debt service | B80: =IF(B79<1,"n/a",(B27-B45)/B79) -> -2.8854765 | C80: =IF(C79<1,"n/a",(C27-C45)/C79) -> -0.44895536 | D80: =IF(D79<1,"n/a",(D27-D45)/D79) -> 1.43035 | E80: =IF(E79<1,"n/a",(E27-E45)/E79) -> 2.1639475 | F80: =IF(F79<1,"n/a",(F27-F45)/F79) -> n/a
A81: Net margin excl. grants (% of sales) | B81: =IF(B7=0,0,B36/B7) -> -2.6648107 | C81: =IF(C7=0,0,C36/C7) -> -0.3058935 | D81: =IF(D7=0,0,D36/D7) -> 0.084154101 | E81: =IF(E7=0,0,E36/E7) -> 0.11914882 | F81: =IF(F7=0,0,F36/F7) -> 0.13046936
A83: Operating statistics (kg fresh weight)
A84: Raw feedstock collected | B84: =SUMIF(Monthly!$C$4:$BJ$4,1,Monthly!$C$15:$BJ$15) -> 25066.667 | C84: =SUMIF(Monthly!$C$4:$BJ$4,2,Monthly!$C$15:$BJ$15) -> 79466.667 | D84: =SUMIF(Monthly!$C$4:$BJ$4,3,Monthly!$C$15:$BJ$15) -> 108800 | E84: =SUMIF(Monthly!$C$4:$BJ$4,4,Monthly!$C$15:$BJ$15) -> 108800 | F84: =SUMIF(Monthly!$C$4:$BJ$4,5,Monthly!$C$15:$BJ$15) -> 108800 | G84: =SUM(B84:F84) -> 430933.33
A85: of which poultry litter | B85: =SUMIF(Monthly!$C$4:$BJ$4,1,Monthly!$C$16:$BJ$16) -> 4000 | C85: =SUMIF(Monthly!$C$4:$BJ$4,2,Monthly!$C$16:$BJ$16) -> 8000 | D85: =SUMIF(Monthly!$C$4:$BJ$4,3,Monthly!$C$16:$BJ$16) -> 8000 | E85: =SUMIF(Monthly!$C$4:$BJ$4,4,Monthly!$C$16:$BJ$16) -> 8000 | F85: =SUMIF(Monthly!$C$4:$BJ$4,5,Monthly!$C$16:$BJ$16) -> 8000 | G85: =SUM(B85:F85) -> 36000
A86: of which other feedstock | B86: =SUMIF(Monthly!$C$4:$BJ$4,1,Monthly!$C$17:$BJ$17) -> 21066.667 | C86: =SUMIF(Monthly!$C$4:$BJ$4,2,Monthly!$C$17:$BJ$17) -> 71466.667 | D86: =SUMIF(Monthly!$C$4:$BJ$4,3,Monthly!$C$17:$BJ$17) -> 100800 | E86: =SUMIF(Monthly!$C$4:$BJ$4,4,Monthly!$C$17:$BJ$17) -> 100800 | F86: =SUMIF(Monthly!$C$4:$BJ$4,5,Monthly!$C$17:$BJ$17) -> 100800 | G86: =SUM(B86:F86) -> 394933.33
A87: Bed feed loaded | B87: =SUMIF(Monthly!$C$4:$BJ$4,1,Monthly!$C$14:$BJ$14) -> 18800 | C87: =SUMIF(Monthly!$C$4:$BJ$4,2,Monthly!$C$14:$BJ$14) -> 59600 | D87: =SUMIF(Monthly!$C$4:$BJ$4,3,Monthly!$C$14:$BJ$14) -> 81600 | E87: =SUMIF(Monthly!$C$4:$BJ$4,4,Monthly!$C$14:$BJ$14) -> 81600 | F87: =SUMIF(Monthly!$C$4:$BJ$4,5,Monthly!$C$14:$BJ$14) -> 81600 | G87: =SUM(B87:F87) -> 323200
A88: Unscreened vermicompost harvested | B88: =SUMIF(Monthly!$C$4:$BJ$4,1,Monthly!$C$18:$BJ$18) -> 3250 | C88: =SUMIF(Monthly!$C$4:$BJ$4,2,Monthly!$C$18:$BJ$18) -> 16055 | D88: =SUMIF(Monthly!$C$4:$BJ$4,3,Monthly!$C$18:$BJ$18) -> 26065 | E88: =SUMIF(Monthly!$C$4:$BJ$4,4,Monthly!$C$18:$BJ$18) -> 26520 | F88: =SUMIF(Monthly!$C$4:$BJ$4,5,Monthly!$C$18:$BJ$18) -> 26520 | G88: =SUM(B88:F88) -> 98410
A89: Saleable vermicompost produced | B89: =SUMIF(Monthly!$C$4:$BJ$4,1,Monthly!$C$21:$BJ$21) -> 2600 | C89: =SUMIF(Monthly!$C$4:$BJ$4,2,Monthly!$C$21:$BJ$21) -> 12844 | D89: =SUMIF(Monthly!$C$4:$BJ$4,3,Monthly!$C$21:$BJ$21) -> 20852 | E89: =SUMIF(Monthly!$C$4:$BJ$4,4,Monthly!$C$21:$BJ$21) -> 21216 | F89: =SUMIF(Monthly!$C$4:$BJ$4,5,Monthly!$C$21:$BJ$21) -> 21216 | G89: =SUM(B89:F89) -> 78728
A90: Vermicompost sold | B90: =SUMIF(Monthly!$C$4:$BJ$4,1,Monthly!$C$25:$BJ$25) -> 2513.3333 | C90: =SUMIF(Monthly!$C$4:$BJ$4,2,Monthly!$C$25:$BJ$25) -> 11670.333 | D90: =SUMIF(Monthly!$C$4:$BJ$4,3,Monthly!$C$25:$BJ$25) -> 20959.667 | E90: =SUMIF(Monthly!$C$4:$BJ$4,4,Monthly!$C$25:$BJ$25) -> 21216 | F90: =SUMIF(Monthly!$C$4:$BJ$4,5,Monthly!$C$25:$BJ$25) -> 21216 | G90: =SUM(B90:F90) -> 77575.333
A91: Demand reachable | B91: =SUMIF(Monthly!$C$4:$BJ$4,1,Monthly!$C$24:$BJ$24) -> 8800 | C91: =SUMIF(Monthly!$C$4:$BJ$4,2,Monthly!$C$24:$BJ$24) -> 15400 | D91: =SUMIF(Monthly!$C$4:$BJ$4,3,Monthly!$C$24:$BJ$24) -> 22000 | E91: =SUMIF(Monthly!$C$4:$BJ$4,4,Monthly!$C$24:$BJ$24) -> 22000 | F91: =SUMIF(Monthly!$C$4:$BJ$4,5,Monthly!$C$24:$BJ$24) -> 22000 | G91: =SUM(B91:F91) -> 90200
A92: Closing inventory (kg) | B92: =INDEX(Monthly!$C$26:$BJ$26,1,12) -> 86.666667 | C92: =INDEX(Monthly!$C$26:$BJ$26,1,24) -> 1260.3333 | D92: =INDEX(Monthly!$C$26:$BJ$26,1,36) -> 1152.6667 | E92: =INDEX(Monthly!$C$26:$BJ$26,1,48) -> 1152.6667 | F92: =INDEX(Monthly!$C$26:$BJ$26,1,60) -> 1152.6667
A93: Beds in operation at year end | B93: =INDEX(Monthly!$C$10:$BJ$10,1,1*12)+INDEX(Monthly!$C$11:$BJ$11,1,1*12) -> 16 | C93: =INDEX(Monthly!$C$10:$BJ$10,1,2*12)+INDEX(Monthly!$C$11:$BJ$11,1,2*12) -> 32 | D93: =INDEX(Monthly!$C$10:$BJ$10,1,3*12)+INDEX(Monthly!$C$11:$BJ$11,1,3*12) -> 32 | E93: =INDEX(Monthly!$C$10:$BJ$10,1,4*12)+INDEX(Monthly!$C$11:$BJ$11,1,4*12) -> 32 | F93: =INDEX(Monthly!$C$10:$BJ$10,1,5*12)+INDEX(Monthly!$C$11:$BJ$11,1,5*12) -> 32

Sheet Returns
A1: Integrated Vermicompost Unit (proposed new component) - Investment appraisal (nominal ETB). Phase 2 investment is brought forward to PY0 for simplicity (conservative).
B3: PY0 (investment) | C3: PY1 | D3: PY2 | E3: PY3 | F3: PY4 | G3: PY5
A4: A. Full economic view - all investment counted, including grant-funded and in-kind assets; grant income excluded
A5: Investment (all fixed assets at full value) | B5: =-(Assumptions!$F$76+Assumptions!$F$77+Assumptions!$F$9*(Assumptions!$F$78+Assumptions!$F$79)) -> -213000 | C5: 0 | D5: 0 | E5: 0 | F5: 0 | G5: 0
A6: EBITDA excluding grants | B6: 0 | C6: =Annual!B27 -> -77759.444 | D6: =Annual!C27 -> -24689.964 | E6: =Annual!D27 -> 78661.028 | F6: =Annual!E27 -> 93310.108 | G6: =Annual!F27 -> 104507.32
A7: Less tax paid | B7: 0 | C7: =-Annual!B45 -> 0 | D7: =-Annual!C45 -> 0 | E7: =-Annual!D45 -> 0 | F7: =-Annual!E45 -> -4056.6026 | G7: =-Annual!F45 -> -6509.0071
A8: Less increase in working capital (receivables/inventory) | B8: 0 | C8: =-((Annual!B61+Annual!B62)-(0)) -> -2465.8889 | D8: =-((Annual!C61+Annual!C62)-(Annual!B61+Annual!B62)) -> -7731.5556 | E8: =-((Annual!D61+Annual!D62)-(Annual!C61+Annual!C62)) -> -2659.1799 | F8: =-((Annual!E61+Annual!E62)-(Annual!D61+Annual!D62)) -> -1542.7949 | G8: =-((Annual!F61+Annual!F62)-(Annual!E61+Annual!E62)) -> -1727.9303
A9: Residual value: net book value of fixed assets + working capital at end PY5 (conservative) | B9: 0 | C9: 0 | D9: 0 | E9: 0 | F9: 0 | G9: =Annual!F65+Annual!F61+Annual!F62 -> 134234.02
A10: Net cash flow | B10: =SUM(B5:B9) -> -213000 | C10: =SUM(C5:C9) -> -80225.333 | D10: =SUM(D5:D9) -> -32421.52 | E10: =SUM(E5:E9) -> 76001.849 | F10: =SUM(F5:F9) -> 87710.71 | G10: =SUM(G5:G9) -> 230504.4
A11: Cumulative net cash flow | B11: =B10 -> -213000 | C11: =B11+C10 -> -293225.33 | D11: =C11+D10 -> -325646.85 | E11: =D11+E10 -> -249645 | F11: =E11+F10 -> -161934.29 | G11: =F11+G10 -> 68570.105
A13: B. Enterprise view - grant-funded and in-kind assets and inputs treated as free to the enterprise
A14: Investment funded by the enterprise (cash capex) | B14: =-(Assumptions!$F$76+Assumptions!$F$77-Assumptions!$F$80+Assumptions!$F$9*(Assumptions!$F$78+Assumptions!$F$79)) -> -213000 | C14: 0 | D14: 0 | E14: 0 | F14: 0 | G14: 0
A15: EBITDA excl. grants + in-kind grant inputs - tax - change in working capital | B15: 0 | C15: =C6+Annual!B32+C7+C8 -> -80225.333 | D15: =D6+Annual!C32+D7+D8 -> -32421.52 | E15: =E6+Annual!D32+E7+E8 -> 76001.849 | F15: =F6+Annual!E32+F7+F8 -> 87710.71 | G15: =G6+Annual!F32+G7+G8 -> 96270.383
A16: Residual value (as above) | B16: 0 | C16: 0 | D16: 0 | E16: 0 | F16: 0 | G16: =G9 -> 134234.02
A17: Net cash flow | B17: =SUM(B14:B16) -> -213000 | C17: =SUM(C14:C16) -> -80225.333 | D17: =SUM(D14:D16) -> -32421.52 | E17: =SUM(E14:E16) -> 76001.849 | F17: =SUM(F14:F16) -> 87710.71 | G17: =SUM(G14:G16) -> 230504.4
A18: Cumulative net cash flow | B18: =B17 -> -213000 | C18: =B18+C17 -> -293225.33 | D18: =C18+D17 -> -325646.85 | E18: =D18+E17 -> -249645 | F18: =E18+F17 -> -161934.29 | G18: =F18+G17 -> 68570.105
A20: Results
A21: Discount rate (nominal ETB; see Assumptions note) | B21: =Assumptions!$F$94 -> 0.25
A22: A. NPV at discount rate | B22: =B10+NPV(Assumptions!$F$94,C10:G10) -> -147559.1
A23: A. IRR | B23: =IFERROR(IRR(B10:G10),"not defined") -> 0.049671036
A24: A. Payback (years from PY0) | B24: =IF(G11<0,"> 5 years",COUNTIF(C11:G11,"<0")+(-INDEX(B11:G11,1,COUNTIF(C11:G11,"<0")+1))/INDEX(C10:G10,1,COUNTIF(C11:G11,"<0")+1)) -> 4.7025215
A25: B. NPV at discount rate | B25: =B17+NPV(Assumptions!$F$94,C17:G17) -> -147559.1
A26: B. IRR | B26: =IFERROR(IRR(B17:G17),"not defined") -> 0.049671036
A27: B. Payback (years from PY0) | B27: =IF(G18<0,"> 5 years",COUNTIF(C18:G18,"<0")+(-INDEX(B18:G18,1,COUNTIF(C18:G18,"<0")+1))/INDEX(C17:G17,1,COUNTIF(C18:G18,"<0")+1)) -> 4.7025215
A29: Notes: PY0 investment is placed at the start of PY1 for simplicity (actual capex occurs in model month 3-4). Residual value is book value, not market value. All flows are nominal ETB: prices and costs escalate annually at the separate price and cost escalation rates on the Assumptions sheet, consistent with a nominal discount rate.

Sheet Unit_BreakEven
A1: Unit economics and break-even per kg saleable vermicompost (PY1 prices, steady state, active scenario)
A3: Raw feedstock per kg saleable product (kg) | B3: =Assumptions!$F$26 -> 5.1282051
A4: Feedstock cost per kg (all purchased feedstock; litter would lower this) | B4: =B3*Assumptions!$F$31 -> 2.5641026
A5: Casual handling + screening labour per kg | B5: =B3*Assumptions!$F$58+Assumptions!$F$57/(1-Assumptions!$F$23-Assumptions!$F$24) -> 1.5192308
A6: Bag + delivery per kg | B6: =Assumptions!$F$56/Assumptions!$F$55+Assumptions!$F$59 -> 2
A7: Total variable cost per kg | B7: =B4+B5+B6 -> 6.0833333
A8: Selling price per kg | B8: =Assumptions!$F$36 -> 16
A9: Contribution per kg | B9: =B8-B7 -> 9.9166667
A10: Contribution margin % | B10: =IF(B8=0,0,B9/B8) -> 0.61979167
A11: Fixed costs at full operation (PY3, deflated to PY1 prices) | B11: =Annual!D26/(1+Assumptions!$F$41)^2 -> 158180
A12: Depreciation PY3 | B12: =Annual!D28 -> 24680
A13: Interest PY3 | B13: =Annual!D30 -> 13415.003
A14: Accounting break-even volume (t/yr) | B14: =IF(B9<=0,"no break-even",(B11+B12+B13)/B9/1000) -> 19.792437
A15: Break-even revenue (ETB/yr, PY1 prices) | B15: =IF(ISNUMBER(B14),B14*1000*B8,"n/a") -> 316679
A16: Planned sales PY3 (t) | B16: =Annual!D90/1000 -> 20.959667
A17: Production capacity PY3 (t saleable) | B17: =Annual!D89/1000 -> 20.852
A18: Break-even PRICE at planned PY3 volume (ETB/kg, PY1 prices) | B18: =B7+(B11+B12+B13)/(B16*1000) -> 15.447748
A19: Margin of safety on volume | B19: =IF(ISNUMBER(B14),(B16-B14)/B16,"n/a") -> 0.055689312
A20: Return to paid + unpaid member labour per day worked, PY3 (ETB/day; 24 days/FTE-month) | B20: =(Annual!D27+Annual!D18)/((Assumptions!$F$61+Assumptions!$F$9*Assumptions!$F$62)*12*24+Annual!D37/Assumptions!$F$63*24) -> 349.53393
